{
"meta":{"test_sets":[],"test_metrics":[],"learn_metrics":[{"best_value":"Min","name":"MultiClass"}],"launch_mode":"Train","parameters":"","iteration_count":1000,"learn_sets":["learn"],"name":"experiment"},
"iterations":[
{"learn":[1.087521824],"iteration":0,"passed_time":0.03318028575,"remaining_time":33.14710547},
{"learn":[1.074749143],"iteration":1,"passed_time":0.04266856008,"remaining_time":21.29161148},
{"learn":[1.063468013],"iteration":2,"passed_time":0.04857837807,"remaining_time":16.14421431},
{"learn":[1.053298587],"iteration":3,"passed_time":0.05879350988,"remaining_time":14.63958396},
{"learn":[1.045621033],"iteration":4,"passed_time":0.06559353938,"remaining_time":13.05311434},
{"learn":[1.034669116],"iteration":5,"passed_time":0.07613911868,"remaining_time":12.61371399},
{"learn":[1.027576435],"iteration":6,"passed_time":0.08091590573,"remaining_time":11.4784992},
{"learn":[1.019973124],"iteration":7,"passed_time":0.08551929085,"remaining_time":10.60439207},
{"learn":[1.013664591],"iteration":8,"passed_time":0.09254585411,"remaining_time":10.19032682},
{"learn":[1.008148644],"iteration":9,"passed_time":0.09682263163,"remaining_time":9.585440531},
{"learn":[1.002494153],"iteration":10,"passed_time":0.1021351329,"remaining_time":9.182876948},
{"learn":[0.9940362653],"iteration":11,"passed_time":0.109343768,"remaining_time":9.002636901},
{"learn":[0.989922983],"iteration":12,"passed_time":0.1147120065,"remaining_time":8.709288496},
{"learn":[0.9829387009],"iteration":13,"passed_time":0.1234853073,"remaining_time":8.696893785},
{"learn":[0.9772962105],"iteration":14,"passed_time":0.1290241067,"remaining_time":8.472583004},
{"learn":[0.9718068565],"iteration":15,"passed_time":0.1376846005,"remaining_time":8.46760293},
{"learn":[0.9666232047],"iteration":16,"passed_time":0.1421375925,"remaining_time":8.218897259},
{"learn":[0.9607824122],"iteration":17,"passed_time":0.146607487,"remaining_time":7.9982529},
{"learn":[0.9549663085],"iteration":18,"passed_time":0.1551244637,"remaining_time":8.009320997},
{"learn":[0.9496914052],"iteration":19,"passed_time":0.161300776,"remaining_time":7.903738023},
{"learn":[0.9437118393],"iteration":20,"passed_time":0.1676689087,"remaining_time":7.816564838},
{"learn":[0.9396148454],"iteration":21,"passed_time":0.1737144953,"remaining_time":7.722398926},
{"learn":[0.9356897209],"iteration":22,"passed_time":0.1785101598,"remaining_time":7.582801134},
{"learn":[0.9318272475],"iteration":23,"passed_time":0.1866263732,"remaining_time":7.58947251},
{"learn":[0.9272444365],"iteration":24,"passed_time":0.1919112514,"remaining_time":7.484538805},
{"learn":[0.9235737802],"iteration":25,"passed_time":0.1964898521,"remaining_time":7.36081215},
{"learn":[0.9179114829],"iteration":26,"passed_time":0.2068447979,"remaining_time":7.454073641},
{"learn":[0.9160737799],"iteration":27,"passed_time":0.2114837504,"remaining_time":7.341507336},
{"learn":[0.9128563739],"iteration":28,"passed_time":0.2213022556,"remaining_time":7.409810006},
{"learn":[0.9074411346],"iteration":29,"passed_time":0.2269236004,"remaining_time":7.337196412},
{"learn":[0.9014569233],"iteration":30,"passed_time":0.2356627551,"remaining_time":7.366361602},
{"learn":[0.8973800856],"iteration":31,"passed_time":0.2405226213,"remaining_time":7.275809293},
{"learn":[0.8921849939],"iteration":32,"passed_time":0.2450927223,"remaining_time":7.181959469},
{"learn":[0.8872243834],"iteration":33,"passed_time":0.2530600603,"remaining_time":7.189882889},
{"learn":[0.8836937449],"iteration":34,"passed_time":0.2577585189,"remaining_time":7.106770591},
{"learn":[0.8791464202],"iteration":35,"passed_time":0.2635973992,"remaining_time":7.058552578},
{"learn":[0.8752116909],"iteration":36,"passed_time":0.2703673759,"remaining_time":7.036859001},
{"learn":[0.8724703644],"iteration":37,"passed_time":0.275192621,"remaining_time":6.966718459},
{"learn":[0.8699484279],"iteration":38,"passed_time":0.283445945,"remaining_time":6.9843988},
{"learn":[0.8665615702],"iteration":39,"passed_time":0.2883133649,"remaining_time":6.919520759},
{"learn":[0.8616460829],"iteration":40,"passed_time":0.2926354725,"remaining_time":6.844815077},
{"learn":[0.857495251],"iteration":41,"passed_time":0.3006125256,"remaining_time":6.85682856},
{"learn":[0.8544227983],"iteration":42,"passed_time":0.3051923496,"remaining_time":6.792304153},
{"learn":[0.8520737853],"iteration":43,"passed_time":0.3098664185,"remaining_time":6.732552185},
{"learn":[0.8475048969],"iteration":44,"passed_time":0.3184604719,"remaining_time":6.758438905},
{"learn":[0.8435458757],"iteration":45,"passed_time":0.3242843606,"remaining_time":6.725375653},
{"learn":[0.8398370849],"iteration":46,"passed_time":0.3338768699,"remaining_time":6.76988632},
{"learn":[0.8366261946],"iteration":47,"passed_time":0.3408252949,"remaining_time":6.759701682},
{"learn":[0.8335876489],"iteration":48,"passed_time":0.3507107936,"remaining_time":6.806652342},
{"learn":[0.8302495185],"iteration":49,"passed_time":0.3562347039,"remaining_time":6.768459374},
{"learn":[0.8264282567],"iteration":50,"passed_time":0.3648983947,"remaining_time":6.78997209},
{"learn":[0.8235689067],"iteration":51,"passed_time":0.369647875,"remaining_time":6.738965106},
{"learn":[0.8200429567],"iteration":52,"passed_time":0.3749313869,"remaining_time":6.699245724},
{"learn":[0.8176564501],"iteration":53,"passed_time":0.3836039085,"remaining_time":6.720172175},
{"learn":[0.8147885383],"iteration":54,"passed_time":0.3895524504,"remaining_time":6.693219375},
{"learn":[0.8122126336],"iteration":55,"passed_time":0.3989926888,"remaining_time":6.725876754},
{"learn":[0.80875074],"iteration":56,"passed_time":0.4053068078,"remaining_time":6.705338944},
{"learn":[0.8044447353],"iteration":57,"passed_time":0.4146259149,"remaining_time":6.734096757},
{"learn":[0.8005443795],"iteration":58,"passed_time":0.4217166274,"remaining_time":6.72602282},
{"learn":[0.7974757036],"iteration":59,"passed_time":0.4313583745,"remaining_time":6.757947867},
{"learn":[0.7942186629],"iteration":60,"passed_time":0.4382059103,"remaining_time":6.745497537},
{"learn":[0.7923506516],"iteration":61,"passed_time":0.4481416196,"remaining_time":6.77994902},
{"learn":[0.7894306304],"iteration":62,"passed_time":0.4541492529,"remaining_time":6.754569047},
{"learn":[0.7873321393],"iteration":63,"passed_time":0.4639835063,"remaining_time":6.78575878},
{"learn":[0.7835679902],"iteration":64,"passed_time":0.47023904,"remaining_time":6.76420773},
{"learn":[0.7786841561],"iteration":65,"passed_time":0.4798771779,"remaining_time":6.790989154},
{"learn":[0.7755449977],"iteration":66,"passed_time":0.485298165,"remaining_time":6.757958029},
{"learn":[0.772035837],"iteration":67,"passed_time":0.4945898653,"remaining_time":6.778790506},
{"learn":[0.7695913346],"iteration":68,"passed_time":0.5000028038,"remaining_time":6.746414642},
{"learn":[0.7671736061],"iteration":69,"passed_time":0.5060703941,"remaining_time":6.723506665},
{"learn":[0.7641119263],"iteration":70,"passed_time":0.516465713,"remaining_time":6.757699259},
{"learn":[0.7627054205],"iteration":71,"passed_time":0.5274338068,"remaining_time":6.798035732},
{"learn":[0.7604919664],"iteration":72,"passed_time":0.5336832442,"remaining_time":6.777046128},
{"learn":[0.7575623391],"iteration":73,"passed_time":0.5438381704,"remaining_time":6.805326295},
{"learn":[0.755915035],"iteration":74,"passed_time":0.5499725162,"remaining_time":6.782994367},
{"learn":[0.753112291],"iteration":75,"passed_time":0.5627153629,"remaining_time":6.84143415},
{"learn":[0.7508392239],"iteration":76,"passed_time":0.5672283629,"remaining_time":6.799373752},
{"learn":[0.7459811111],"iteration":77,"passed_time":0.5734030462,"remaining_time":6.777918059},
{"learn":[0.7422422926],"iteration":78,"passed_time":0.5791951292,"remaining_time":6.752388785},
{"learn":[0.7393998565],"iteration":79,"passed_time":0.5836310463,"remaining_time":6.711757032},
{"learn":[0.7350596456],"iteration":80,"passed_time":0.5923865946,"remaining_time":6.721028153},
{"learn":[0.7327185882],"iteration":81,"passed_time":0.5978914599,"remaining_time":6.693467808},
{"learn":[0.7302258038],"iteration":82,"passed_time":0.6028307791,"remaining_time":6.660190656},
{"learn":[0.7274216854],"iteration":83,"passed_time":0.6104667262,"remaining_time":6.6569943},
{"learn":[0.7255687835],"iteration":84,"passed_time":0.6158623496,"remaining_time":6.629577057},
{"learn":[0.7229287595],"iteration":85,"passed_time":0.6247033054,"remaining_time":6.639288618},
{"learn":[0.721054398],"iteration":86,"passed_time":0.630005373,"remaining_time":6.611435696},
{"learn":[0.718854262],"iteration":87,"passed_time":0.6355219768,"remaining_time":6.586318669},
{"learn":[0.7158702551],"iteration":88,"passed_time":0.6446047474,"remaining_time":6.598145224},
{"learn":[0.7127122688],"iteration":89,"passed_time":0.65035097,"remaining_time":6.575770919},
{"learn":[0.709201851],"iteration":90,"passed_time":0.6575545927,"remaining_time":6.568320053},
{"learn":[0.7059135464],"iteration":91,"passed_time":0.6618986326,"remaining_time":6.532651721},
{"learn":[0.7024395352],"iteration":92,"passed_time":0.66642609,"remaining_time":6.499445845},
{"learn":[0.6994632145],"iteration":93,"passed_time":0.672667833,"remaining_time":6.483372944},
{"learn":[0.697048458],"iteration":94,"passed_time":0.6776958424,"remaining_time":6.455944604},
{"learn":[0.6933367578],"iteration":95,"passed_time":0.6820490115,"remaining_time":6.422628191},
{"learn":[0.6890959606],"iteration":96,"passed_time":0.6894525822,"remaining_time":6.418305998},
{"learn":[0.6851638907],"iteration":97,"passed_time":0.6948876717,"remaining_time":6.395802856},
{"learn":[0.6836595722],"iteration":98,"passed_time":0.7029639916,"remaining_time":6.397682388},
{"learn":[0.681755717],"iteration":99,"passed_time":0.7081545017,"remaining_time":6.373390515},
{"learn":[0.6802221094],"iteration":100,"passed_time":0.7126959783,"remaining_time":6.343699847},
{"learn":[0.6776511395],"iteration":101,"passed_time":0.7197558393,"remaining_time":6.336673958},
{"learn":[0.6766111239],"iteration":102,"passed_time":0.7243783276,"remaining_time":6.30842097},
{"learn":[0.6745617906],"iteration":103,"passed_time":0.728483521,"remaining_time":6.27616572},
{"learn":[0.6702916076],"iteration":104,"passed_time":0.7356408864,"remaining_time":6.270462794},
{"learn":[0.668234965],"iteration":105,"passed_time":0.7411896733,"remaining_time":6.251165735},
{"learn":[0.6649668924],"iteration":106,"passed_time":0.7456824712,"remaining_time":6.223312587},
{"learn":[0.6624280689],"iteration":107,"passed_time":0.7521196844,"remaining_time":6.211951468},
{"learn":[0.659497744],"iteration":108,"passed_time":0.7565699259,"remaining_time":6.184438569},
{"learn":[0.6577166436],"iteration":109,"passed_time":0.7610393557,"remaining_time":6.157500242},
{"learn":[0.6553454721],"iteration":110,"passed_time":0.7677868442,"remaining_time":6.149211752},
{"learn":[0.6528125928],"iteration":111,"passed_time":0.7735890755,"remaining_time":6.133456242},
{"learn":[0.6507273889],"iteration":112,"passed_time":0.7783197346,"remaining_time":6.109465527},
{"learn":[0.6485478652],"iteration":113,"passed_time":0.7860436537,"remaining_time":6.109076115},
{"learn":[0.6456569556],"iteration":114,"passed_time":0.7909817872,"remaining_time":6.08712071},
{"learn":[0.6419270138],"iteration":115,"passed_time":0.7958273678,"remaining_time":6.064753389},
{"learn":[0.6404196122],"iteration":116,"passed_time":0.803203655,"remaining_time":6.061784849},
{"learn":[0.6383126426],"iteration":117,"passed_time":0.8090196071,"remaining_time":6.047078758},
{"learn":[0.6359655584],"iteration":118,"passed_time":0.8160041924,"remaining_time":6.041173895},
{"learn":[0.6349748653],"iteration":119,"passed_time":0.8214535835,"remaining_time":6.023992945},
{"learn":[0.6333785192],"iteration":120,"passed_time":0.8279910727,"remaining_time":6.014910355},
{"learn":[0.6320082758],"iteration":121,"passed_time":0.8355694469,"remaining_time":6.013360446},
{"learn":[0.6303694849],"iteration":122,"passed_time":0.8410996218,"remaining_time":5.997108686},
{"learn":[0.6282099199],"iteration":123,"passed_time":0.8489997996,"remaining_time":5.997772778},
{"learn":[0.6261763559],"iteration":124,"passed_time":0.8536915826,"remaining_time":5.975841078},
{"learn":[0.6225601227],"iteration":125,"passed_time":0.8580980199,"remaining_time":5.952203726},
{"learn":[0.6201773325],"iteration":126,"passed_time":0.8646794208,"remaining_time":5.943819956},
{"learn":[0.6170468713],"iteration":127,"passed_time":0.8694893915,"remaining_time":5.923396479},
{"learn":[0.6156312569],"iteration":128,"passed_time":0.873648766,"remaining_time":5.898822288},
{"learn":[0.6132159022],"iteration":129,"passed_time":0.8785249625,"remaining_time":5.879359365},
{"learn":[0.6112377925],"iteration":130,"passed_time":0.8842279725,"remaining_time":5.865603879},
{"learn":[0.609634697],"iteration":131,"passed_time":0.8888547464,"remaining_time":5.844893332},
{"learn":[0.6075210257],"iteration":132,"passed_time":0.8945010274,"remaining_time":5.831070607},
{"learn":[0.6050272841],"iteration":133,"passed_time":0.9005269675,"remaining_time":5.819823537},
{"learn":[0.6031914106],"iteration":134,"passed_time":0.9050490823,"remaining_time":5.799018194},
{"learn":[0.6015089091],"iteration":135,"passed_time":0.9116678345,"remaining_time":5.791772125},
{"learn":[0.5986378603],"iteration":136,"passed_time":0.9162304624,"remaining_time":5.771583132},
{"learn":[0.5954834539],"iteration":137,"passed_time":0.9207332371,"remaining_time":5.751246742},
{"learn":[0.5932423534],"iteration":138,"passed_time":0.9260655295,"remaining_time":5.736276409},
{"learn":[0.5910545327],"iteration":139,"passed_time":0.9315012791,"remaining_time":5.722079286},
{"learn":[0.5894184552],"iteration":140,"passed_time":0.9356075801,"remaining_time":5.699907173},
{"learn":[0.5873574111],"iteration":141,"passed_time":0.9399588859,"remaining_time":5.679469888},
{"learn":[0.5860568993],"iteration":142,"passed_time":0.9468702919,"remaining_time":5.674600281},
{"learn":[0.5840058891],"iteration":143,"passed_time":0.9513506097,"remaining_time":5.655250846},
{"learn":[0.5831340726],"iteration":144,"passed_time":0.9556678674,"remaining_time":5.635145011},
{"learn":[0.5815215555],"iteration":145,"passed_time":0.9623057567,"remaining_time":5.628829563},
{"learn":[0.5791703285],"iteration":146,"passed_time":0.9672258648,"remaining_time":5.612541923},
{"learn":[0.5775529365],"iteration":147,"passed_time":0.9713283036,"remaining_time":5.591700775},
{"learn":[0.5745016605],"iteration":148,"passed_time":0.9782580731,"remaining_time":5.58723235},
{"learn":[0.5712205462],"iteration":149,"passed_time":0.9828937964,"remaining_time":5.569731513},
{"learn":[0.5682557951],"iteration":150,"passed_time":0.9872663742,"remaining_time":5.550921534},
{"learn":[0.5663618992],"iteration":151,"passed_time":0.9940474332,"remaining_time":5.545738312},
{"learn":[0.5644738128],"iteration":152,"passed_time":0.9985048704,"remaining_time":5.527670753},
{"learn":[0.5627275829],"iteration":153,"passed_time":1.002728026,"remaining_time":5.508492923},
{"learn":[0.5602168996],"iteration":154,"passed_time":1.010724556,"remaining_time":5.510079029},
{"learn":[0.558487159],"iteration":155,"passed_time":1.016929184,"remaining_time":5.501847638},
{"learn":[0.5556830322],"iteration":156,"passed_time":1.023217747,"remaining_time":5.494092741},
{"learn":[0.5528370024],"iteration":157,"passed_time":1.028406409,"remaining_time":5.480494916},
{"learn":[0.5507961493],"iteration":158,"passed_time":1.03273479,"remaining_time":5.462452568},
{"learn":[0.547281059],"iteration":159,"passed_time":1.037644291,"remaining_time":5.447632529},
{"learn":[0.5442078705],"iteration":160,"passed_time":1.043646789,"remaining_time":5.438631403},
{"learn":[0.5427997413],"iteration":161,"passed_time":1.048096034,"remaining_time":5.421632571},
{"learn":[0.5413422964],"iteration":162,"passed_time":1.05366195,"remaining_time":5.410521795},
{"learn":[0.5395739077],"iteration":163,"passed_time":1.058914322,"remaining_time":5.397880323},
{"learn":[0.5377466258],"iteration":164,"passed_time":1.063557259,"remaining_time":5.382244313},
{"learn":[0.5357698774],"iteration":165,"passed_time":1.071200584,"remaining_time":5.38181498},
{"learn":[0.5322597855],"iteration":166,"passed_time":1.075798478,"remaining_time":5.366108574},
{"learn":[0.5307437035],"iteration":167,"passed_time":1.080191402,"remaining_time":5.349519325},
{"learn":[0.5295562323],"iteration":168,"passed_time":1.088930523,"remaining_time":5.354445352},
{"learn":[0.5275414038],"iteration":169,"passed_time":1.094740196,"remaining_time":5.344908016},
{"learn":[0.5252733518],"iteration":170,"passed_time":1.099222174,"remaining_time":5.328977676},
{"learn":[0.5228859499],"iteration":171,"passed_time":1.106463894,"remaining_time":5.326465722},
{"learn":[0.5213166974],"iteration":172,"passed_time":1.111585429,"remaining_time":5.313763873},
{"learn":[0.5193424368],"iteration":173,"passed_time":1.121281391,"remaining_time":5.322864534},
{"learn":[0.5162873066],"iteration":174,"passed_time":1.129043239,"remaining_time":5.322632414},
{"learn":[0.5146132034],"iteration":175,"passed_time":1.142364189,"remaining_time":5.348341432},
{"learn":[0.5129155918],"iteration":176,"passed_time":1.15321098,"remaining_time":5.362105291},
{"learn":[0.5116527459],"iteration":177,"passed_time":1.158814859,"remaining_time":5.351380978},
{"learn":[0.5100318053],"iteration":178,"passed_time":1.169350305,"remaining_time":5.363332963},
{"learn":[0.508014974],"iteration":179,"passed_time":1.174998845,"remaining_time":5.352772517},
{"learn":[0.505522548],"iteration":180,"passed_time":1.179614759,"remaining_time":5.337593853},
{"learn":[0.5037726324],"iteration":181,"passed_time":1.187243094,"remaining_time":5.336070611},
{"learn":[0.5016717283],"iteration":182,"passed_time":1.192370369,"remaining_time":5.323314709},
{"learn":[0.4996009095],"iteration":183,"passed_time":1.196957234,"remaining_time":5.308245126},
{"learn":[0.4979863241],"iteration":184,"passed_time":1.204408377,"remaining_time":5.305907173},
{"learn":[0.49658458],"iteration":185,"passed_time":1.209023021,"remaining_time":5.291100746},
{"learn":[0.4951514997],"iteration":186,"passed_time":1.213851168,"remaining_time":5.277331549},
{"learn":[0.4937458606],"iteration":187,"passed_time":1.221331807,"remaining_time":5.275113974},
{"learn":[0.4930637228],"iteration":188,"passed_time":1.225881857,"remaining_time":5.260265536},
{"learn":[0.4920092882],"iteration":189,"passed_time":1.230620534,"remaining_time":5.246329643},
{"learn":[0.4910857541],"iteration":190,"passed_time":1.239227329,"remaining_time":5.248873871},
{"learn":[0.4891024772],"iteration":191,"passed_time":1.243835507,"remaining_time":5.234474424},
{"learn":[0.4879261554],"iteration":192,"passed_time":1.25052312,"remaining_time":5.228871286},
{"learn":[0.4866184446],"iteration":193,"passed_time":1.254994725,"remaining_time":5.214050249},
{"learn":[0.4859627436],"iteration":194,"passed_time":1.25951658,"remaining_time":5.199542804},
{"learn":[0.4849244413],"iteration":195,"passed_time":1.266282043,"remaining_time":5.194340625},
{"learn":[0.4836226912],"iteration":196,"passed_time":1.27150916,"remaining_time":5.182852057},
{"learn":[0.4823940511],"iteration":197,"passed_time":1.275861228,"remaining_time":5.167882347},
{"learn":[0.4813353765],"iteration":198,"passed_time":1.282431357,"remaining_time":5.161947322},
{"learn":[0.4802590403],"iteration":199,"passed_time":1.287074075,"remaining_time":5.148296299},
{"learn":[0.4785945999],"iteration":200,"passed_time":1.291489847,"remaining_time":5.133832776},
{"learn":[0.4771864064],"iteration":201,"passed_time":1.296480884,"remaining_time":5.121741315},
{"learn":[0.475322648],"iteration":202,"passed_time":1.301959422,"remaining_time":5.11163379},
{"learn":[0.4737659798],"iteration":203,"passed_time":1.306261247,"remaining_time":5.096980159},
{"learn":[0.4722768192],"iteration":204,"passed_time":1.311537811,"remaining_time":5.086207607},
{"learn":[0.470347812],"iteration":205,"passed_time":1.317691807,"remaining_time":5.078870363},
{"learn":[0.4680956545],"iteration":206,"passed_time":1.322540906,"remaining_time":5.066545596},
{"learn":[0.4653506182],"iteration":207,"passed_time":1.329418764,"remaining_time":5.0620176},
{"learn":[0.4643010009],"iteration":208,"passed_time":1.33433291,"remaining_time":5.05003508},
{"learn":[0.4626290475],"iteration":209,"passed_time":1.3392964,"remaining_time":5.038305503},
{"learn":[0.4617605925],"iteration":210,"passed_time":1.346336063,"remaining_time":5.034403572},
{"learn":[0.4600444215],"iteration":211,"passed_time":1.351404852,"remaining_time":5.023146338},
{"learn":[0.4586040371],"iteration":212,"passed_time":1.355616362,"remaining_time":5.008779703},
{"learn":[0.4578384468],"iteration":213,"passed_time":1.362467956,"remaining_time":5.004204737},
{"learn":[0.4560481341],"iteration":214,"passed_time":1.367218754,"remaining_time":4.99193824},
{"learn":[0.4550670141],"iteration":215,"passed_time":1.371364109,"remaining_time":4.977543801},
{"learn":[0.4536382612],"iteration":216,"passed_time":1.377866269,"remaining_time":4.971747875},
{"learn":[0.4525415085],"iteration":217,"passed_time":1.382843835,"remaining_time":4.960476509},
{"learn":[0.4517838664],"iteration":218,"passed_time":1.387028461,"remaining_time":4.946434832},
{"learn":[0.4506385339],"iteration":219,"passed_time":1.392594514,"remaining_time":4.937380551},
{"learn":[0.4495855827],"iteration":220,"passed_time":1.397685471,"remaining_time":4.926683178},
{"learn":[0.4479544091],"iteration":221,"passed_time":1.402028786,"remaining_time":4.913416197},
{"learn":[0.4463966982],"iteration":222,"passed_time":1.406709862,"remaining_time":4.901406111},
{"learn":[0.4447197198],"iteration":223,"passed_time":1.4132019,"remaining_time":4.895735153},
{"learn":[0.4436264652],"iteration":224,"passed_time":1.417681767,"remaining_time":4.883126085},
{"learn":[0.4428651224],"iteration":225,"passed_time":1.422252948,"remaining_time":4.870901688},
{"learn":[0.4419088359],"iteration":226,"passed_time":1.428830923,"remaining_time":4.86557843},
{"learn":[0.4403480064],"iteration":227,"passed_time":1.432958774,"remaining_time":4.851948128},
{"learn":[0.4396253837],"iteration":228,"passed_time":1.437330708,"remaining_time":4.839222604},
{"learn":[0.4385128549],"iteration":229,"passed_time":1.444556425,"remaining_time":4.836123684},
{"learn":[0.4373774815],"iteration":230,"passed_time":1.449120786,"remaining_time":4.824129369},
{"learn":[0.4363502384],"iteration":231,"passed_time":1.45333345,"remaining_time":4.81103487},
{"learn":[0.4353979285],"iteration":232,"passed_time":1.45992926,"remaining_time":4.805861554},
{"learn":[0.4337752492],"iteration":233,"passed_time":1.464325451,"remaining_time":4.793475622},
{"learn":[0.4323697036],"iteration":234,"passed_time":1.468699253,"remaining_time":4.781084804},
{"learn":[0.4319073694],"iteration":235,"passed_time":1.475407414,"remaining_time":4.776318916},
{"learn":[0.4311619107],"iteration":236,"passed_time":1.479994972,"remaining_time":4.764709552},
{"learn":[0.4303179559],"iteration":237,"passed_time":1.48435928,"remaining_time":4.752444418},
{"learn":[0.4292321583],"iteration":238,"passed_time":1.49172773,"remaining_time":4.74981089},
{"learn":[0.4285669046],"iteration":239,"passed_time":1.496848149,"remaining_time":4.740019138},
{"learn":[0.4272513229],"iteration":240,"passed_time":1.501154437,"remaining_time":4.727702147},
{"learn":[0.4260554434],"iteration":241,"passed_time":1.507976214,"remaining_time":4.723330455},
{"learn":[0.4250387329],"iteration":242,"passed_time":1.51306327,"remaining_time":4.713534549},
{"learn":[0.4241155728],"iteration":243,"passed_time":1.517185431,"remaining_time":4.700787648},
{"learn":[0.4229333678],"iteration":244,"passed_time":1.52479014,"remaining_time":4.698843085},
{"learn":[0.4214365183],"iteration":245,"passed_time":1.529084806,"remaining_time":4.686707089},
{"learn":[0.4207759458],"iteration":246,"passed_time":1.53321581,"remaining_time":4.674135647},
{"learn":[0.4197132014],"iteration":247,"passed_time":1.540744827,"remaining_time":4.671935927},
{"learn":[0.4185205519],"iteration":248,"passed_time":1.545431192,"remaining_time":4.661119778},
{"learn":[0.4172821132],"iteration":249,"passed_time":1.549591244,"remaining_time":4.648773731},
{"learn":[0.4163880891],"iteration":250,"passed_time":1.55717947,"remaining_time":4.6467228},
{"learn":[0.4149636226],"iteration":251,"passed_time":1.562353592,"remaining_time":4.63746225},
{"learn":[0.4137995889],"iteration":252,"passed_time":1.56693465,"remaining_time":4.626482938},
{"learn":[0.4124356445],"iteration":253,"passed_time":1.574054686,"remaining_time":4.623011008},
{"learn":[0.4107222155],"iteration":254,"passed_time":1.580975278,"remaining_time":4.618927772},
{"learn":[0.4097530426],"iteration":255,"passed_time":1.588927097,"remaining_time":4.617819376},
{"learn":[0.4088046355],"iteration":256,"passed_time":1.593798848,"remaining_time":4.60775309},
{"learn":[0.4070653594],"iteration":257,"passed_time":1.598868842,"remaining_time":4.598297213},
{"learn":[0.4060420253],"iteration":258,"passed_time":1.608046813,"remaining_time":4.600628141},
{"learn":[0.4054542722],"iteration":259,"passed_time":1.613742282,"remaining_time":4.592958803},
{"learn":[0.4040780466],"iteration":260,"passed_time":1.624993796,"remaining_time":4.601036072},
{"learn":[0.4029727177],"iteration":261,"passed_time":1.632798416,"remaining_time":4.599256606},
{"learn":[0.4022350896],"iteration":262,"passed_time":1.646564027,"remaining_time":4.614135697},
{"learn":[0.4013379253],"iteration":263,"passed_time":1.661187486,"remaining_time":4.631189355},
{"learn":[0.4004832414],"iteration":264,"passed_time":1.676082892,"remaining_time":4.648758209},
{"learn":[0.3995112561],"iteration":265,"passed_time":1.682179286,"remaining_time":4.641802992},
{"learn":[0.3987949386],"iteration":266,"passed_time":1.691125902,"remaining_time":4.642678975},
{"learn":[0.3975574248],"iteration":267,"passed_time":1.698175249,"remaining_time":4.638299559},
{"learn":[0.3964658836],"iteration":268,"passed_time":1.708422578,"remaining_time":4.642590722},
{"learn":[0.3953899416],"iteration":269,"passed_time":1.714960305,"remaining_time":4.636744528},
{"learn":[0.3945325801],"iteration":270,"passed_time":1.725014727,"remaining_time":4.640353269},
{"learn":[0.393231895],"iteration":271,"passed_time":1.730793706,"remaining_time":4.63241845},
{"learn":[0.3921459793],"iteration":272,"passed_time":1.74040472,"remaining_time":4.634704145},
{"learn":[0.3913263867],"iteration":273,"passed_time":1.745831381,"remaining_time":4.625815994},
{"learn":[0.3904905121],"iteration":274,"passed_time":1.755964795,"remaining_time":4.629361733},
{"learn":[0.3898070352],"iteration":275,"passed_time":1.761762444,"remaining_time":4.621434817},
{"learn":[0.3888316316],"iteration":276,"passed_time":1.770176999,"remaining_time":4.620353683},
{"learn":[0.3880193186],"iteration":277,"passed_time":1.774841897,"remaining_time":4.609481474},
{"learn":[0.3875674548],"iteration":278,"passed_time":1.779546116,"remaining_time":4.598755374},
{"learn":[0.3866262636],"iteration":279,"passed_time":1.787621117,"remaining_time":4.596740014},
{"learn":[0.3860398156],"iteration":280,"passed_time":1.79256177,"remaining_time":4.586661611},
{"learn":[0.3848938958],"iteration":281,"passed_time":1.801303678,"remaining_time":4.586298016},
{"learn":[0.3836738607],"iteration":282,"passed_time":1.806345739,"remaining_time":4.576501395},
{"learn":[0.3823485076],"iteration":283,"passed_time":1.811183569,"remaining_time":4.566223365},
{"learn":[0.3814433449],"iteration":284,"passed_time":1.820421687,"remaining_time":4.567022828},
{"learn":[0.3803605287],"iteration":285,"passed_time":1.826233901,"remaining_time":4.559199319},
{"learn":[0.379084993],"iteration":286,"passed_time":1.834253054,"remaining_time":4.556872571},
{"learn":[0.3784853338],"iteration":287,"passed_time":1.840054994,"remaining_time":4.549024845},
{"learn":[0.3772209557],"iteration":288,"passed_time":1.845480039,"remaining_time":4.540264041},
{"learn":[0.3765252907],"iteration":289,"passed_time":1.855824124,"remaining_time":4.543569408},
{"learn":[0.3758052736],"iteration":290,"passed_time":1.86243249,"remaining_time":4.537679161},
{"learn":[0.3748969077],"iteration":291,"passed_time":1.871615773,"remaining_time":4.538027286},
{"learn":[0.373625637],"iteration":292,"passed_time":1.879014583,"remaining_time":4.534004471},
{"learn":[0.3723395281],"iteration":293,"passed_time":1.88785631,"remaining_time":4.533423655},
{"learn":[0.3716805873],"iteration":294,"passed_time":1.893862814,"remaining_time":4.526011133},
{"learn":[0.3708100876],"iteration":295,"passed_time":1.901746057,"remaining_time":4.523071702},
{"learn":[0.3696553758],"iteration":296,"passed_time":1.906813566,"remaining_time":4.513434131},
{"learn":[0.3686909767],"iteration":297,"passed_time":1.915496568,"remaining_time":4.512344264},
{"learn":[0.3677519613],"iteration":298,"passed_time":1.922112581,"remaining_time":4.506357589},
{"learn":[0.3667447894],"iteration":299,"passed_time":1.931434853,"remaining_time":4.506681325},
{"learn":[0.3657412944],"iteration":300,"passed_time":1.937187362,"remaining_time":4.49865105},
{"learn":[0.3648814201],"iteration":301,"passed_time":1.941764722,"remaining_time":4.487919787},
{"learn":[0.3641677975],"iteration":302,"passed_time":1.952060466,"remaining_time":4.490383315},
{"learn":[0.3629568449],"iteration":303,"passed_time":1.956663823,"remaining_time":4.479730331},
{"learn":[0.362402486],"iteration":304,"passed_time":1.964452156,"remaining_time":4.476374584},
{"learn":[0.3615239931],"iteration":305,"passed_time":1.968862428,"remaining_time":4.465328514},
{"learn":[0.3601926931],"iteration":306,"passed_time":1.974448964,"remaining_time":4.456980887},
{"learn":[0.3591895169],"iteration":307,"passed_time":1.982393945,"remaining_time":4.453950031},
{"learn":[0.3580759128],"iteration":308,"passed_time":1.987940829,"remaining_time":4.445524637},
{"learn":[0.3571685409],"iteration":309,"passed_time":1.993545522,"remaining_time":4.437246484},
{"learn":[0.3561164999],"iteration":310,"passed_time":2.001886488,"remaining_time":4.435047558},
{"learn":[0.3548920767],"iteration":311,"passed_time":2.006783132,"remaining_time":4.425214085},
{"learn":[0.3536171415],"iteration":312,"passed_time":2.014659667,"remaining_time":4.421952687},
{"learn":[0.3530231933],"iteration":313,"passed_time":2.019303604,"remaining_time":4.411599593},
{"learn":[0.3523309766],"iteration":314,"passed_time":2.024725725,"remaining_time":4.40297499},
{"learn":[0.3518604697],"iteration":315,"passed_time":2.030733715,"remaining_time":4.3956388},
{"learn":[0.351289276],"iteration":316,"passed_time":2.035558487,"remaining_time":4.38576166},
{"learn":[0.3505712966],"iteration":317,"passed_time":2.043955965,"remaining_time":4.383578516},
{"learn":[0.3501169143],"iteration":318,"passed_time":2.048631625,"remaining_time":4.373411086},
{"learn":[0.349440218],"iteration":319,"passed_time":2.05319219,"remaining_time":4.363033403},
{"learn":[0.3481468284],"iteration":320,"passed_time":2.061259699,"remaining_time":4.360110079},
{"learn":[0.3474541089],"iteration":321,"passed_time":2.067112446,"remaining_time":4.352491423},
{"learn":[0.3465380042],"iteration":322,"passed_time":2.075267348,"remaining_time":4.349708961},
{"learn":[0.3456382803],"iteration":323,"passed_time":2.079992022,"remaining_time":4.339736441},
{"learn":[0.3451912483],"iteration":324,"passed_time":2.084429395,"remaining_time":4.329199512},
{"learn":[0.344219392],"iteration":325,"passed_time":2.092156962,"remaining_time":4.325502431},
{"learn":[0.3437846709],"iteration":326,"passed_time":2.096829213,"remaining_time":4.31549254},
{"learn":[0.3422545774],"iteration":327,"passed_time":2.101399355,"remaining_time":4.305305996},
{"learn":[0.3413831511],"iteration":328,"passed_time":2.110689257,"remaining_time":4.304779609},
{"learn":[0.340505849],"iteration":329,"passed_time":2.115853696,"remaining_time":4.29582417},
{"learn":[0.3397300161],"iteration":330,"passed_time":2.123868561,"remaining_time":4.292652772},
{"learn":[0.3393341954],"iteration":331,"passed_time":2.129254898,"remaining_time":4.284163469},
{"learn":[0.3383216881],"iteration":332,"passed_time":2.133770162,"remaining_time":4.273948042},
{"learn":[0.3371929404],"iteration":333,"passed_time":2.142166851,"remaining_time":4.271506355},
{"learn":[0.3367454158],"iteration":334,"passed_time":2.14811442,"remaining_time":4.26416743},
{"learn":[0.3362404871],"iteration":335,"passed_time":2.153106817,"remaining_time":4.254949185},
{"learn":[0.3352931458],"iteration":336,"passed_time":2.159756078,"remaining_time":4.249015667},
{"learn":[0.3347162874],"iteration":337,"passed_time":2.164305468,"remaining_time":4.238965147},
{"learn":[0.3342993919],"iteration":338,"passed_time":2.17052754,"remaining_time":4.232208567},
{"learn":[0.3337928642],"iteration":339,"passed_time":2.17573648,"remaining_time":4.223488461},
{"learn":[0.3329925934],"iteration":340,"passed_time":2.18046938,"remaining_time":4.213868978},
{"learn":[0.3322708768],"iteration":341,"passed_time":2.187933928,"remaining_time":4.209533698},
{"learn":[0.3307860115],"iteration":342,"passed_time":2.192646023,"remaining_time":4.199907979},
{"learn":[0.3299221671],"iteration":343,"passed_time":2.196977088,"remaining_time":4.189584214},
{"learn":[0.3292716509],"iteration":344,"passed_time":2.204684633,"remaining_time":4.185705607},
{"learn":[0.3289592693],"iteration":345,"passed_time":2.20931507,"remaining_time":4.175988601},
{"learn":[0.3283219756],"iteration":346,"passed_time":2.21373911,"remaining_time":4.165912505},
{"learn":[0.3273471207],"iteration":347,"passed_time":2.221821686,"remaining_time":4.162723388},
{"learn":[0.3264142526],"iteration":348,"passed_time":2.228222988,"remaining_time":4.156370101},
{"learn":[0.3256357337],"iteration":349,"passed_time":2.235587881,"remaining_time":4.151806065},
{"learn":[0.3249930187],"iteration":350,"passed_time":2.241570559,"remaining_time":4.144670349},
{"learn":[0.3241093408],"iteration":351,"passed_time":2.246539319,"remaining_time":4.135674655},
{"learn":[0.3233418724],"iteration":352,"passed_time":2.256856074,"remaining_time":4.136503909},
{"learn":[0.3216441001],"iteration":353,"passed_time":2.262840733,"remaining_time":4.129364727},
{"learn":[0.3206043119],"iteration":354,"passed_time":2.271249457,"remaining_time":4.126636338},
{"learn":[0.3200666379],"iteration":355,"passed_time":2.276546637,"remaining_time":4.118247287},
{"learn":[0.3194054244],"iteration":356,"passed_time":2.283903012,"remaining_time":4.113584417},
{"learn":[0.3186592684],"iteration":357,"passed_time":2.289116712,"remaining_time":4.105064048},
{"learn":[0.3182467497],"iteration":358,"passed_time":2.294254791,"remaining_time":4.096427078},
{"learn":[0.3175676234],"iteration":359,"passed_time":2.30425116,"remaining_time":4.096446506},
{"learn":[0.3167055373],"iteration":360,"passed_time":2.31169827,"remaining_time":4.091898046},
{"learn":[0.3156739319],"iteration":361,"passed_time":2.320252343,"remaining_time":4.089284516},
{"learn":[0.3146542742],"iteration":362,"passed_time":2.326037103,"remaining_time":4.081778607},
{"learn":[0.3141122791],"iteration":363,"passed_time":2.334645014,"remaining_time":4.079214915},
{"learn":[0.3137270764],"iteration":364,"passed_time":2.340808941,"remaining_time":4.07236624},
{"learn":[0.313057945],"iteration":365,"passed_time":2.34944109,"remaining_time":4.069796861},
{"learn":[0.3121974823],"iteration":366,"passed_time":2.355410698,"remaining_time":4.062602103},
{"learn":[0.3115812276],"iteration":367,"passed_time":2.360427922,"remaining_time":4.053778387},
{"learn":[0.3109789557],"iteration":368,"passed_time":2.369913865,"remaining_time":4.052616934},
{"learn":[0.3103738879],"iteration":369,"passed_time":2.375717163,"remaining_time":4.045140035},
{"learn":[0.3094836326],"iteration":370,"passed_time":2.386861414,"remaining_time":4.046727303},
{"learn":[0.3085320746],"iteration":371,"passed_time":2.390785363,"remaining_time":4.03605701},
{"learn":[0.3077324148],"iteration":372,"passed_time":2.399039188,"remaining_time":4.032701262},
{"learn":[0.3069936179],"iteration":373,"passed_time":2.404720573,"remaining_time":4.02501358},
{"learn":[0.3064529473],"iteration":374,"passed_time":2.409477394,"remaining_time":4.015795656},
{"learn":[0.3056989231],"iteration":375,"passed_time":2.417465707,"remaining_time":4.011964365},
{"learn":[0.3051561519],"iteration":376,"passed_time":2.421459769,"remaining_time":4.001510441},
{"learn":[0.3042158701],"iteration":377,"passed_time":2.42574137,"remaining_time":3.991563841},
{"learn":[0.3034274242],"iteration":378,"passed_time":2.432698196,"remaining_time":3.986030554},
{"learn":[0.3028593293],"iteration":379,"passed_time":2.436968646,"remaining_time":3.976106738},
{"learn":[0.3022666383],"iteration":380,"passed_time":2.441208752,"remaining_time":3.9661633},
{"learn":[0.3017497723],"iteration":381,"passed_time":2.448784166,"remaining_time":3.961645589},
{"learn":[0.3008376811],"iteration":382,"passed_time":2.453038908,"remaining_time":3.951762418},
{"learn":[0.2999396457],"iteration":383,"passed_time":2.457547717,"remaining_time":3.942316129},
{"learn":[0.2990196581],"iteration":384,"passed_time":2.465641982,"remaining_time":3.938622906},
{"learn":[0.2985676721],"iteration":385,"passed_time":2.471616891,"remaining_time":3.931535677},
{"learn":[0.2977059611],"iteration":386,"passed_time":2.477175137,"remaining_time":3.923794209},
{"learn":[0.296937372],"iteration":387,"passed_time":2.483852715,"remaining_time":3.91782954},
{"learn":[0.2963812146],"iteration":388,"passed_time":2.488305557,"remaining_time":3.908366826},
{"learn":[0.2957610826],"iteration":389,"passed_time":2.496097018,"remaining_time":3.904151747},
{"learn":[0.2948112592],"iteration":390,"passed_time":2.50129686,"remaining_time":3.895881811},
{"learn":[0.2941718449],"iteration":391,"passed_time":2.50639453,"remaining_time":3.887469066},
{"learn":[0.2931213996],"iteration":392,"passed_time":2.514210773,"remaining_time":3.88327211},
{"learn":[0.292729866],"iteration":393,"passed_time":2.518558603,"remaining_time":3.873722116},
{"learn":[0.2920035287],"iteration":394,"passed_time":2.52315639,"remaining_time":3.864581307},
{"learn":[0.2912905288],"iteration":395,"passed_time":2.530205122,"remaining_time":3.859201751},
{"learn":[0.2904490358],"iteration":396,"passed_time":2.534719978,"remaining_time":3.849965104},
{"learn":[0.289873808],"iteration":397,"passed_time":2.538731126,"remaining_time":3.839990296},
{"learn":[0.2895960057],"iteration":398,"passed_time":2.546050927,"remaining_time":3.83502909},
{"learn":[0.2884439982],"iteration":399,"passed_time":2.550638506,"remaining_time":3.825957759},
{"learn":[0.2880741581],"iteration":400,"passed_time":2.55493655,"remaining_time":3.816476293},
{"learn":[0.2874251496],"iteration":401,"passed_time":2.562972916,"remaining_time":3.812581602},
{"learn":[0.2870163126],"iteration":402,"passed_time":2.567492853,"remaining_time":3.803457154},
{"learn":[0.2864018171],"iteration":403,"passed_time":2.57197494,"remaining_time":3.794299664},
{"learn":[0.2861991045],"iteration":404,"passed_time":2.580257273,"remaining_time":3.790748339},
{"learn":[0.2854271405],"iteration":405,"passed_time":2.585141275,"remaining_time":3.782201766},
{"learn":[0.2846799645],"iteration":406,"passed_time":2.593347053,"remaining_time":3.778513029},
{"learn":[0.2838182254],"iteration":407,"passed_time":2.598354135,"remaining_time":3.770160902},
{"learn":[0.2831654958],"iteration":408,"passed_time":2.602762478,"remaining_time":3.760959961},
{"learn":[0.2824746908],"iteration":409,"passed_time":2.611557928,"remaining_time":3.758095555},
{"learn":[0.2819710963],"iteration":410,"passed_time":2.61606616,"remaining_time":3.749058317},
{"learn":[0.2808389282],"iteration":411,"passed_time":2.620737974,"remaining_time":3.740276525},
{"learn":[0.2801150785],"iteration":412,"passed_time":2.629045847,"remaining_time":3.736682596},
{"learn":[0.2795593456],"iteration":413,"passed_time":2.633587503,"remaining_time":3.727734968},
{"learn":[0.2791547577],"iteration":414,"passed_time":2.639062123,"remaining_time":3.720123715},
{"learn":[0.2779117248],"iteration":415,"passed_time":2.646850602,"remaining_time":3.715771037},
{"learn":[0.2773752229],"iteration":416,"passed_time":2.651412208,"remaining_time":3.706890449},
{"learn":[0.2763937046],"iteration":417,"passed_time":2.660052981,"remaining_time":3.703710131},
{"learn":[0.2759226614],"iteration":418,"passed_time":2.665436964,"remaining_time":3.695987772},
{"learn":[0.2753830312],"iteration":419,"passed_time":2.671754636,"remaining_time":3.689565926},
{"learn":[0.274856077],"iteration":420,"passed_time":2.679388789,"remaining_time":3.684955128},
{"learn":[0.2740963287],"iteration":421,"passed_time":2.684191373,"remaining_time":3.676451691},
{"learn":[0.2733998599],"iteration":422,"passed_time":2.693244586,"remaining_time":3.673763891},
{"learn":[0.2728972084],"iteration":423,"passed_time":2.698023497,"remaining_time":3.665239468},
{"learn":[0.2725822907],"iteration":424,"passed_time":2.706258943,"remaining_time":3.661409158},
{"learn":[0.2718347703],"iteration":425,"passed_time":2.712158702,"remaining_time":3.654411021},
{"learn":[0.2707879311],"iteration":426,"passed_time":2.722908961,"remaining_time":3.653927014},
{"learn":[0.2704298956],"iteration":427,"passed_time":2.728688337,"remaining_time":3.646751702},
{"learn":[0.2699233816],"iteration":428,"passed_time":2.736767761,"remaining_time":3.642644269},
{"learn":[0.2695586063],"iteration":429,"passed_time":2.742776726,"remaining_time":3.6357738},
{"learn":[0.2691621295],"iteration":430,"passed_time":2.748051124,"remaining_time":3.627937563},
{"learn":[0.2686744362],"iteration":431,"passed_time":2.75863544,"remaining_time":3.627094745},
{"learn":[0.2683953753],"iteration":432,"passed_time":2.76355469,"remaining_time":3.618788705},
{"learn":[0.2679290525],"iteration":433,"passed_time":2.773511535,"remaining_time":3.617068039},
{"learn":[0.2673715497],"iteration":434,"passed_time":2.779112808,"remaining_time":3.609652268},
{"learn":[0.2668870834],"iteration":435,"passed_time":2.794566502,"remaining_time":3.614989695},
{"learn":[0.2658666178],"iteration":436,"passed_time":2.806231091,"remaining_time":3.615350353},
{"learn":[0.2647849167],"iteration":437,"passed_time":2.81123684,"remaining_time":3.607112109},
{"learn":[0.2644983995],"iteration":438,"passed_time":2.817901327,"remaining_time":3.601008301},
{"learn":[0.2637087989],"iteration":439,"passed_time":2.822480871,"remaining_time":3.592248382},
{"learn":[0.2632700356],"iteration":440,"passed_time":2.826601649,"remaining_time":3.5829259},
{"learn":[0.2628000987],"iteration":441,"passed_time":2.834330678,"remaining_time":3.578182169},
{"learn":[0.262550921],"iteration":442,"passed_time":2.838739204,"remaining_time":3.56924997},
{"learn":[0.2622793334],"iteration":443,"passed_time":2.843048512,"remaining_time":3.560213902},
{"learn":[0.261477927],"iteration":444,"passed_time":2.85194278,"remaining_time":3.556917399},
{"learn":[0.2609517784],"iteration":445,"passed_time":2.856367417,"remaining_time":3.548043832},
{"learn":[0.2596669952],"iteration":446,"passed_time":2.860643616,"remaining_time":3.539006532},
{"learn":[0.259095196],"iteration":447,"passed_time":2.873370307,"remaining_time":3.5404027},
{"learn":[0.2583220826],"iteration":448,"passed_time":2.880470264,"remaining_time":3.534830992},
{"learn":[0.2579338773],"iteration":449,"passed_time":2.889125293,"remaining_time":3.531153136},
{"learn":[0.2574311614],"iteration":450,"passed_time":2.896016925,"remaining_time":3.525306634},
{"learn":[0.2568995537],"iteration":451,"passed_time":2.901436565,"remaining_time":3.51767088},
{"learn":[0.2561724499],"iteration":452,"passed_time":2.906213521,"remaining_time":3.509268866},
{"learn":[0.2554132898],"iteration":453,"passed_time":2.91587875,"remaining_time":3.506761669},
{"learn":[0.2551327862],"iteration":454,"passed_time":2.920534574,"remaining_time":3.498222732},
{"learn":[0.2548005274],"iteration":455,"passed_time":2.925768187,"remaining_time":3.490390117},
{"learn":[0.25447209],"iteration":456,"passed_time":2.933940714,"remaining_time":3.486060848},
{"learn":[0.2540206136],"iteration":457,"passed_time":2.938930093,"remaining_time":3.47794784},
{"learn":[0.2537253695],"iteration":458,"passed_time":2.948987778,"remaining_time":3.475822196},
{"learn":[0.2529396796],"iteration":459,"passed_time":2.971372329,"remaining_time":3.488132734},
{"learn":[0.251701489],"iteration":460,"passed_time":2.998162342,"remaining_time":3.505443606},
{"learn":[0.2511678181],"iteration":461,"passed_time":3.012187586,"remaining_time":3.507698964},
{"learn":[0.2508995258],"iteration":462,"passed_time":3.034530341,"remaining_time":3.51953087},
{"learn":[0.2505392777],"iteration":463,"passed_time":3.063235795,"remaining_time":3.538565488},
{"learn":[0.2500983661],"iteration":464,"passed_time":3.080048097,"remaining_time":3.543711252},
{"learn":[0.249701301],"iteration":465,"passed_time":3.097959014,"remaining_time":3.550021703},
{"learn":[0.2490258787],"iteration":466,"passed_time":3.105788307,"remaining_time":3.544721986},
{"learn":[0.2483948285],"iteration":467,"passed_time":3.116533229,"remaining_time":3.542725807},
{"learn":[0.2476243174],"iteration":468,"passed_time":3.128830408,"remaining_time":3.542449779},
{"learn":[0.2470464988],"iteration":469,"passed_time":3.136312648,"remaining_time":3.536692986},
{"learn":[0.2466545164],"iteration":470,"passed_time":3.14837373,"remaining_time":3.536071556},
{"learn":[0.2461863749],"iteration":471,"passed_time":3.162302378,"remaining_time":3.537490795},
{"learn":[0.2454090406],"iteration":472,"passed_time":3.169467438,"remaining_time":3.531309387},
{"learn":[0.2449648573],"iteration":473,"passed_time":3.180842545,"remaining_time":3.529795736},
{"learn":[0.2444237831],"iteration":474,"passed_time":3.18813149,"remaining_time":3.523724278},
{"learn":[0.2436889052],"iteration":475,"passed_time":3.198761942,"remaining_time":3.521326171},
{"learn":[0.2432705237],"iteration":476,"passed_time":3.209067072,"remaining_time":3.518536853},
{"learn":[0.2424343327],"iteration":477,"passed_time":3.216033359,"remaining_time":3.512069903},
{"learn":[0.2421315431],"iteration":478,"passed_time":3.227444609,"remaining_time":3.510435576},
{"learn":[0.2416772882],"iteration":479,"passed_time":3.236726326,"remaining_time":3.50645352},
{"learn":[0.2413617337],"iteration":480,"passed_time":3.247006369,"remaining_time":3.503526623},
{"learn":[0.2408938333],"iteration":481,"passed_time":3.259793558,"remaining_time":3.503263616},
{"learn":[0.2404997141],"iteration":482,"passed_time":3.268801719,"remaining_time":3.498903703},
{"learn":[0.2400739203],"iteration":483,"passed_time":3.280969337,"remaining_time":3.497892929},
{"learn":[0.2397925023],"iteration":484,"passed_time":3.292734274,"remaining_time":3.496408559},
{"learn":[0.2395025761],"iteration":485,"passed_time":3.299946267,"remaining_time":3.490066628},
{"learn":[0.2389520221],"iteration":486,"passed_time":3.313389005,"remaining_time":3.490284517},
{"learn":[0.2381351539],"iteration":487,"passed_time":3.325412201,"remaining_time":3.488957063},
{"learn":[0.2377444051],"iteration":488,"passed_time":3.333027364,"remaining_time":3.482979516},
{"learn":[0.2374847083],"iteration":489,"passed_time":3.341602045,"remaining_time":3.477993966},
{"learn":[0.2369888984],"iteration":490,"passed_time":3.347713418,"remaining_time":3.470440183},
{"learn":[0.2367820171],"iteration":491,"passed_time":3.35659625,"remaining_time":3.465753852},
{"learn":[0.2362761828],"iteration":492,"passed_time":3.362459442,"remaining_time":3.457945106},
{"learn":[0.2358118323],"iteration":493,"passed_time":3.37078704,"remaining_time":3.452668506},
{"learn":[0.2355254645],"iteration":494,"passed_time":3.376054871,"remaining_time":3.444258},
{"learn":[0.2353287631],"iteration":495,"passed_time":3.381136055,"remaining_time":3.435670508},
{"learn":[0.2348608161],"iteration":496,"passed_time":3.389617055,"remaining_time":3.430537985},
{"learn":[0.2345300318],"iteration":497,"passed_time":3.394745461,"remaining_time":3.422012493},
{"learn":[0.2339967855],"iteration":498,"passed_time":3.400189295,"remaining_time":3.413817309},
{"learn":[0.2338154294],"iteration":499,"passed_time":3.407560401,"remaining_time":3.407560401},
{"learn":[0.2332632493],"iteration":500,"passed_time":3.413097376,"remaining_time":3.399472236},
{"learn":[0.2327751563],"iteration":501,"passed_time":3.420888419,"remaining_time":3.393630343},
{"learn":[0.2324943558],"iteration":502,"passed_time":3.426737659,"remaining_time":3.385862061},
{"learn":[0.2320789826],"iteration":503,"passed_time":3.434814931,"remaining_time":3.380294059},
{"learn":[0.2317808256],"iteration":504,"passed_time":3.440385015,"remaining_time":3.372258579},
{"learn":[0.2309331104],"iteration":505,"passed_time":3.445781241,"remaining_time":3.364063109},
{"learn":[0.2304703119],"iteration":506,"passed_time":3.45304338,"remaining_time":3.35769307},
{"learn":[0.229932813],"iteration":507,"passed_time":3.459705708,"remaining_time":3.350738599},
{"learn":[0.2295596862],"iteration":508,"passed_time":3.467289464,"remaining_time":3.34467412},
{"learn":[0.2288450237],"iteration":509,"passed_time":3.474019314,"remaining_time":3.337783263},
{"learn":[0.2280329326],"iteration":510,"passed_time":3.479836383,"remaining_time":3.330019552},
{"learn":[0.2275219876],"iteration":511,"passed_time":3.488836265,"remaining_time":3.325297066},
{"learn":[0.2271384302],"iteration":512,"passed_time":3.494846154,"remaining_time":3.317719449},
{"learn":[0.226656601],"iteration":513,"passed_time":3.503710038,"remaining_time":3.312846456},
{"learn":[0.226252042],"iteration":514,"passed_time":3.509901329,"remaining_time":3.305441057},
{"learn":[0.2258718954],"iteration":515,"passed_time":3.519246487,"remaining_time":3.300998642},
{"learn":[0.2254191471],"iteration":516,"passed_time":3.525819213,"remaining_time":3.293947156},
{"learn":[0.225043862],"iteration":517,"passed_time":3.534407595,"remaining_time":3.28877309},
{"learn":[0.2244851462],"iteration":518,"passed_time":3.540331773,"remaining_time":3.28111673},
{"learn":[0.2240313183],"iteration":519,"passed_time":3.550192438,"remaining_time":3.277100712},
{"learn":[0.2237876993],"iteration":520,"passed_time":3.557064218,"remaining_time":3.270314319},
{"learn":[0.2234416111],"iteration":521,"passed_time":3.565833204,"remaining_time":3.265264888},
{"learn":[0.2232902083],"iteration":522,"passed_time":3.57157178,"remaining_time":3.257437359},
{"learn":[0.222802626],"iteration":523,"passed_time":3.577416999,"remaining_time":3.249714679},
{"learn":[0.2223541738],"iteration":524,"passed_time":3.584971738,"remaining_time":3.243545858},
{"learn":[0.2221284485],"iteration":525,"passed_time":3.590983563,"remaining_time":3.235981386},
{"learn":[0.2218080302],"iteration":526,"passed_time":3.600768572,"remaining_time":3.231809363},
{"learn":[0.2214029815],"iteration":527,"passed_time":3.607230442,"remaining_time":3.224645395},
{"learn":[0.220820954],"iteration":528,"passed_time":3.61536022,"remaining_time":3.218969119},
{"learn":[0.2204272167],"iteration":529,"passed_time":3.622739143,"remaining_time":3.212617731},
{"learn":[0.2200044701],"iteration":530,"passed_time":3.630714148,"remaining_time":3.206788956},
{"learn":[0.2195034155],"iteration":531,"passed_time":3.63808071,"remaining_time":3.200416865},
{"learn":[0.2192960259],"iteration":532,"passed_time":3.64558325,"remaining_time":3.194160183},
{"learn":[0.2189398202],"iteration":533,"passed_time":3.652383913,"remaining_time":3.187286336},
{"learn":[0.2186425471],"iteration":534,"passed_time":3.658707033,"remaining_time":3.179997701},
{"learn":[0.2183920588],"iteration":535,"passed_time":3.666761594,"remaining_time":3.174211529},
{"learn":[0.2180215343],"iteration":536,"passed_time":3.672488507,"remaining_time":3.166410017},
{"learn":[0.217690062],"iteration":537,"passed_time":3.681636829,"remaining_time":3.161554303},
{"learn":[0.2174357303],"iteration":538,"passed_time":3.689011731,"remaining_time":3.155165878},
{"learn":[0.2170649631],"iteration":539,"passed_time":3.699705454,"remaining_time":3.151600943},
{"learn":[0.2166129129],"iteration":540,"passed_time":3.711812973,"remaining_time":3.149209158},
{"learn":[0.2161417235],"iteration":541,"passed_time":3.719941419,"remaining_time":3.143419133},
{"learn":[0.2157429909],"iteration":542,"passed_time":3.729948169,"remaining_time":3.139201314},
{"learn":[0.215408545],"iteration":543,"passed_time":3.735747475,"remaining_time":3.131435383},
{"learn":[0.2148867141],"iteration":544,"passed_time":3.744126275,"remaining_time":3.125830193},
{"learn":[0.2146288651],"iteration":545,"passed_time":3.750347354,"remaining_time":3.118420693},
{"learn":[0.2141423667],"iteration":546,"passed_time":3.756156887,"remaining_time":3.110674716},
{"learn":[0.2135492177],"iteration":547,"passed_time":3.76422591,"remaining_time":3.104799474},
{"learn":[0.2130332084],"iteration":548,"passed_time":3.77032651,"remaining_time":3.097299191},
{"learn":[0.2126828702],"iteration":549,"passed_time":3.779160687,"remaining_time":3.092040562},
{"learn":[0.2124230763],"iteration":550,"passed_time":3.785199299,"remaining_time":3.084490899},
{"learn":[0.2119845876],"iteration":551,"passed_time":3.793919928,"remaining_time":3.07912342},
{"learn":[0.2116389351],"iteration":552,"passed_time":3.801265557,"remaining_time":3.072632376},
{"learn":[0.211078911],"iteration":553,"passed_time":3.811952779,"remaining_time":3.06882841},
{"learn":[0.2107306714],"iteration":554,"passed_time":3.820126287,"remaining_time":3.06298414},
{"learn":[0.2103186475],"iteration":555,"passed_time":3.828662627,"remaining_time":3.057421235},
{"learn":[0.2099436401],"iteration":556,"passed_time":3.834864601,"remaining_time":3.049991056},
{"learn":[0.2097385732],"iteration":557,"passed_time":3.843491111,"remaining_time":3.04448579},
{"learn":[0.2094849108],"iteration":558,"passed_time":3.850827491,"remaining_time":3.037951563},
{"learn":[0.2091094657],"iteration":559,"passed_time":3.86005802,"remaining_time":3.03290273},
{"learn":[0.2085442428],"iteration":560,"passed_time":3.866137064,"remaining_time":3.025372854},
{"learn":[0.2082038839],"iteration":561,"passed_time":3.873511585,"remaining_time":3.018857784},
{"learn":[0.207724346],"iteration":562,"passed_time":3.879705964,"remaining_time":3.011423634},
{"learn":[0.2073616748],"iteration":563,"passed_time":3.885319752,"remaining_time":3.003545056},
{"learn":[0.2070170061],"iteration":564,"passed_time":3.894579536,"remaining_time":2.99848159},
{"learn":[0.2068026633],"iteration":565,"passed_time":3.900534835,"remaining_time":2.990869467},
{"learn":[0.2065491495],"iteration":566,"passed_time":3.910250106,"remaining_time":2.986134561},
{"learn":[0.2061664952],"iteration":567,"passed_time":3.918184764,"remaining_time":2.980027848},
{"learn":[0.2057638281],"iteration":568,"passed_time":3.928450425,"remaining_time":2.975680375},
{"learn":[0.2052475633],"iteration":569,"passed_time":3.938105656,"remaining_time":2.970851636},
{"learn":[0.2048879206],"iteration":570,"passed_time":3.945020328,"remaining_time":2.963946972},
{"learn":[0.2046184252],"iteration":571,"passed_time":3.954954914,"remaining_time":2.959301928},
{"learn":[0.2040882671],"iteration":572,"passed_time":3.963209573,"remaining_time":2.953386541},
{"learn":[0.2036609357],"iteration":573,"passed_time":3.972204922,"remaining_time":2.948012712},
{"learn":[0.2028992028],"iteration":574,"passed_time":3.979115697,"remaining_time":2.941085515},
{"learn":[0.2024935768],"iteration":575,"passed_time":3.988620709,"remaining_time":2.936068022},
{"learn":[0.202297719],"iteration":576,"passed_time":3.994605987,"remaining_time":2.928454649},
{"learn":[0.2020064872],"iteration":577,"passed_time":4.000951261,"remaining_time":2.921109745},
{"learn":[0.2017596062],"iteration":578,"passed_time":4.00880053,"remaining_time":2.914861871},
{"learn":[0.2013222926],"iteration":579,"passed_time":4.014689451,"remaining_time":2.907188912},
{"learn":[0.2011832462],"iteration":580,"passed_time":4.024755281,"remaining_time":2.902534359},
{"learn":[0.2008939195],"iteration":581,"passed_time":4.03176565,"remaining_time":2.895666739},
{"learn":[0.2005293075],"iteration":582,"passed_time":4.04135948,"remaining_time":2.890646489},
{"learn":[0.2002959288],"iteration":583,"passed_time":4.047084371,"remaining_time":2.88285462},
{"learn":[0.1999285998],"iteration":584,"passed_time":4.055412876,"remaining_time":2.876916826},
{"learn":[0.1994516501],"iteration":585,"passed_time":4.061489552,"remaining_time":2.869379991},
{"learn":[0.199206544],"iteration":586,"passed_time":4.070978117,"remaining_time":2.864248658},
{"learn":[0.1987437249],"iteration":587,"passed_time":4.076881873,"remaining_time":2.8565907},
{"learn":[0.1984325679],"iteration":588,"passed_time":4.085739834,"remaining_time":2.851000122},
{"learn":[0.1980553351],"iteration":589,"passed_time":4.091636132,"remaining_time":2.843340363},
{"learn":[0.19767429],"iteration":590,"passed_time":4.097508115,"remaining_time":2.835669744},
{"learn":[0.197372713],"iteration":591,"passed_time":4.106030063,"remaining_time":2.82983153},
{"learn":[0.1970727529],"iteration":592,"passed_time":4.112601058,"remaining_time":2.822645245},
{"learn":[0.1968198286],"iteration":593,"passed_time":4.1213977,"remaining_time":2.816982266},
{"learn":[0.1964104968],"iteration":594,"passed_time":4.127089066,"remaining_time":2.809195079},
{"learn":[0.1961617912],"iteration":595,"passed_time":4.137343791,"remaining_time":2.804508207},
{"learn":[0.1957275772],"iteration":596,"passed_time":4.145776106,"remaining_time":2.79857248},
{"learn":[0.1952048529],"iteration":597,"passed_time":4.154280684,"remaining_time":2.792676981},
{"learn":[0.1949270889],"iteration":598,"passed_time":4.160989419,"remaining_time":2.785570546},
{"learn":[0.1945097757],"iteration":599,"passed_time":4.169837062,"remaining_time":2.779891374},
{"learn":[0.1941643837],"iteration":600,"passed_time":4.17589648,"remaining_time":2.772350575},
{"learn":[0.1939851556],"iteration":601,"passed_time":4.18644381,"remaining_time":2.767781788},
{"learn":[0.1937229705],"iteration":602,"passed_time":4.192531207,"remaining_time":2.760256864},
{"learn":[0.1935312498],"iteration":603,"passed_time":4.200937237,"remaining_time":2.754256864},
{"learn":[0.1932987595],"iteration":604,"passed_time":4.206767487,"remaining_time":2.746567202},
{"learn":[0.1931173931],"iteration":605,"passed_time":4.215211511,"remaining_time":2.740583061},
{"learn":[0.1929930594],"iteration":606,"passed_time":4.221113754,"remaining_time":2.732945149},
{"learn":[0.1926446763],"iteration":607,"passed_time":4.227154627,"remaining_time":2.725402326},
{"learn":[0.1921332103],"iteration":608,"passed_time":4.23491381,"remaining_time":2.718967651},
{"learn":[0.1918537761],"iteration":609,"passed_time":4.240470476,"remaining_time":2.711120469},
{"learn":[0.1915688814],"iteration":610,"passed_time":4.249916534,"remaining_time":2.705757008},
{"learn":[0.1913731182],"iteration":611,"passed_time":4.25620207,"remaining_time":2.698376476},
{"learn":[0.1911635231],"iteration":612,"passed_time":4.26649035,"remaining_time":2.693526534},
{"learn":[0.1907433121],"iteration":613,"passed_time":4.272979422,"remaining_time":2.686270451},
{"learn":[0.1905869453],"iteration":614,"passed_time":4.284066608,"remaining_time":2.681895356},
{"learn":[0.1899798721],"iteration":615,"passed_time":4.291990505,"remaining_time":2.675526549},
{"learn":[0.1895152803],"iteration":616,"passed_time":4.300268534,"remaining_time":2.669372526},
{"learn":[0.189135298],"iteration":617,"passed_time":4.308504987,"remaining_time":2.66318593},
{"learn":[0.1884660831],"iteration":618,"passed_time":4.316854218,"remaining_time":2.657062128},
{"learn":[0.1879392857],"iteration":619,"passed_time":4.326227571,"remaining_time":2.651558834},
{"learn":[0.187674536],"iteration":620,"passed_time":4.33392674,"remaining_time":2.645021312},
{"learn":[0.187138343],"iteration":621,"passed_time":4.34341198,"remaining_time":2.63956548},
{"learn":[0.1869040017],"iteration":622,"passed_time":4.352175905,"remaining_time":2.633660219},
{"learn":[0.1864481862],"iteration":623,"passed_time":4.363591626,"remaining_time":2.629343672},
{"learn":[0.1860198378],"iteration":624,"passed_time":4.375341722,"remaining_time":2.625205033},
{"learn":[0.1859194215],"iteration":625,"passed_time":4.385721984,"remaining_time":2.620223677},
{"learn":[0.18571221],"iteration":626,"passed_time":4.396395664,"remaining_time":2.615399653},
{"learn":[0.185052111],"iteration":627,"passed_time":4.40268655,"remaining_time":2.607960823},
{"learn":[0.1846666865],"iteration":628,"passed_time":4.412356937,"remaining_time":2.602518956},
{"learn":[0.1844616437],"iteration":629,"passed_time":4.41945923,"remaining_time":2.595555421},
{"learn":[0.1842185559],"iteration":630,"passed_time":4.427726108,"remaining_time":2.589272478},
{"learn":[0.1840447072],"iteration":631,"passed_time":4.433530615,"remaining_time":2.581549472},
{"learn":[0.1838509162],"iteration":632,"passed_time":4.441476799,"remaining_time":2.575074226},
{"learn":[0.1834475642],"iteration":633,"passed_time":4.44691154,"remaining_time":2.567144517},
{"learn":[0.1831570578],"iteration":634,"passed_time":4.453024316,"remaining_time":2.559612402},
{"learn":[0.1827786272],"iteration":635,"passed_time":4.460382628,"remaining_time":2.552797605},
{"learn":[0.1825865745],"iteration":636,"passed_time":4.465991064,"remaining_time":2.544983919},
{"learn":[0.1824007934],"iteration":637,"passed_time":4.474100084,"remaining_time":2.538595973},
{"learn":[0.1821624992],"iteration":638,"passed_time":4.480518689,"remaining_time":2.531247647},
{"learn":[0.1817713668],"iteration":639,"passed_time":4.489070896,"remaining_time":2.525102379},
{"learn":[0.181207841],"iteration":640,"passed_time":4.494981222,"remaining_time":2.517469982},
{"learn":[0.1807676345],"iteration":641,"passed_time":4.501310758,"remaining_time":2.510076715},
{"learn":[0.1803044953],"iteration":642,"passed_time":4.508466435,"remaining_time":2.503145439},
{"learn":[0.1798419798],"iteration":643,"passed_time":4.514163145,"remaining_time":2.495406956},
{"learn":[0.1795282817],"iteration":644,"passed_time":4.523474628,"remaining_time":2.48966433},
{"learn":[0.1792554378],"iteration":645,"passed_time":4.529129201,"remaining_time":2.481906714},
{"learn":[0.178896034],"iteration":646,"passed_time":4.537788621,"remaining_time":2.475795028},
{"learn":[0.1784889043],"iteration":647,"passed_time":4.543665124,"remaining_time":2.468163771},
{"learn":[0.178214151],"iteration":648,"passed_time":4.550940912,"remaining_time":2.4612947},
{"learn":[0.1778306446],"iteration":649,"passed_time":4.557146835,"remaining_time":2.453848296},
{"learn":[0.1775055798],"iteration":650,"passed_time":4.562677567,"remaining_time":2.446043734},
{"learn":[0.1770752667],"iteration":651,"passed_time":4.571296237,"remaining_time":2.439894311},
{"learn":[0.1768051265],"iteration":652,"passed_time":4.576830582,"remaining_time":2.432098334},
{"learn":[0.1765706947],"iteration":653,"passed_time":4.585185215,"remaining_time":2.425801352},
{"learn":[0.1763925576],"iteration":654,"passed_time":4.591251929,"remaining_time":2.418293001},
{"learn":[0.1760426975],"iteration":655,"passed_time":4.596926399,"remaining_time":2.410583355},
{"learn":[0.1757426349],"iteration":656,"passed_time":4.604834809,"remaining_time":2.404046179},
{"learn":[0.1754713616],"iteration":657,"passed_time":4.610072231,"remaining_time":2.39611657},
{"learn":[0.1753140532],"iteration":658,"passed_time":4.618445426,"remaining_time":2.38981774},
{"learn":[0.175027344],"iteration":659,"passed_time":4.624250859,"remaining_time":2.382189836},
{"learn":[0.1747073181],"iteration":660,"passed_time":4.630861133,"remaining_time":2.374980218},
{"learn":[0.1743224589],"iteration":661,"passed_time":4.640142535,"remaining_time":2.369136219},
{"learn":[0.1738716669],"iteration":662,"passed_time":4.648706572,"remaining_time":2.362917217},
{"learn":[0.1733632204],"iteration":663,"passed_time":4.655127931,"remaining_time":2.355606905},
{"learn":[0.1730637452],"iteration":664,"passed_time":4.660645939,"remaining_time":2.347844195},
{"learn":[0.1728953192],"iteration":665,"passed_time":4.669789203,"remaining_time":2.341906297},
{"learn":[0.1726403232],"iteration":666,"passed_time":4.675344438,"remaining_time":2.334167463},
{"learn":[0.1722869227],"iteration":667,"passed_time":4.683885835,"remaining_time":2.327919307},
{"learn":[0.1721017042],"iteration":668,"passed_time":4.68951292,"remaining_time":2.320222386},
{"learn":[0.1717870243],"iteration":669,"passed_time":4.696692472,"remaining_time":2.313296292},
{"learn":[0.1715034861],"iteration":670,"passed_time":4.702718799,"remaining_time":2.305804001},
{"learn":[0.1714116225],"iteration":671,"passed_time":4.708163566,"remaining_time":2.298032217},
{"learn":[0.1711404438],"iteration":672,"passed_time":4.716639996,"remaining_time":2.291740385},
{"learn":[0.1707421483],"iteration":673,"passed_time":4.722424459,"remaining_time":2.28414002},
{"learn":[0.1704495065],"iteration":674,"passed_time":4.73308055,"remaining_time":2.278890635},
{"learn":[0.1701709347],"iteration":675,"passed_time":4.740090605,"remaining_time":2.271877746},
{"learn":[0.1699855759],"iteration":676,"passed_time":4.749937382,"remaining_time":2.266218278},
{"learn":[0.1697678917],"iteration":677,"passed_time":4.756845255,"remaining_time":2.259150696},
{"learn":[0.1696842027],"iteration":678,"passed_time":4.770928741,"remaining_time":2.255475885},
{"learn":[0.1694619926],"iteration":679,"passed_time":4.786342704,"remaining_time":2.252396567},
{"learn":[0.1692845665],"iteration":680,"passed_time":4.796378279,"remaining_time":2.246761631},
{"learn":[0.1689978815],"iteration":681,"passed_time":4.806242842,"remaining_time":2.241034053},
{"learn":[0.1687573141],"iteration":682,"passed_time":4.816387379,"remaining_time":2.235424303},
{"learn":[0.1684966446],"iteration":683,"passed_time":4.822118526,"remaining_time":2.22776236},
{"learn":[0.1681978472],"iteration":684,"passed_time":4.830645907,"remaining_time":2.221391913},
{"learn":[0.1677722093],"iteration":685,"passed_time":4.837127235,"remaining_time":2.214078647},
{"learn":[0.1674962109],"iteration":686,"passed_time":4.845860455,"remaining_time":2.207793774},
{"learn":[0.1672705632],"iteration":687,"passed_time":4.851736224,"remaining_time":2.200205962},
{"learn":[0.1671038481],"iteration":688,"passed_time":4.859393994,"remaining_time":2.193427478},
{"learn":[0.1667577149],"iteration":689,"passed_time":4.865353959,"remaining_time":2.185883663},
{"learn":[0.1665561896],"iteration":690,"passed_time":4.870969718,"remaining_time":2.17819051},
{"learn":[0.1661580064],"iteration":691,"passed_time":4.879773253,"remaining_time":2.171922199},
{"learn":[0.1659950784],"iteration":692,"passed_time":4.885238104,"remaining_time":2.16416753},
{"learn":[0.1656521229],"iteration":693,"passed_time":4.893662422,"remaining_time":2.157724353},
{"learn":[0.1652991662],"iteration":694,"passed_time":4.900217571,"remaining_time":2.150455193},
{"learn":[0.165072477],"iteration":695,"passed_time":4.908113638,"remaining_time":2.143773773},
{"learn":[0.1648671176],"iteration":696,"passed_time":4.913865225,"remaining_time":2.136156619},
{"learn":[0.1646752827],"iteration":697,"passed_time":4.925325471,"remaining_time":2.131014746},
{"learn":[0.164307996],"iteration":698,"passed_time":4.933419948,"remaining_time":2.124405443},
{"learn":[0.1641874191],"iteration":699,"passed_time":4.942888357,"remaining_time":2.118380724},
{"learn":[0.1638861856],"iteration":700,"passed_time":4.949020471,"remaining_time":2.11092314},
{"learn":[0.1636104714],"iteration":701,"passed_time":4.958884406,"remaining_time":2.105053494},
{"learn":[0.1633817787],"iteration":702,"passed_time":4.965245679,"remaining_time":2.097692698},
{"learn":[0.1631681699],"iteration":703,"passed_time":4.973302314,"remaining_time":2.091047564},
{"learn":[0.1629454393],"iteration":704,"passed_time":4.979531697,"remaining_time":2.083633831},
{"learn":[0.1626779948],"iteration":705,"passed_time":4.985123699,"remaining_time":2.075958028},
{"learn":[0.1622596039],"iteration":706,"passed_time":4.993079227,"remaining_time":2.069267629},
{"learn":[0.1620504533],"iteration":707,"passed_time":4.998799445,"remaining_time":2.061651749},
{"learn":[0.1619304337],"iteration":708,"passed_time":5.007069943,"remaining_time":2.055087946},
{"learn":[0.1617675368],"iteration":709,"passed_time":5.013287985,"remaining_time":2.047681008},
{"learn":[0.1615177994],"iteration":710,"passed_time":5.021094154,"remaining_time":2.04092294},
{"learn":[0.1614056805],"iteration":711,"passed_time":5.027097493,"remaining_time":2.033432694},
{"learn":[0.1612642043],"iteration":712,"passed_time":5.032895557,"remaining_time":2.02586399},
{"learn":[0.161016805],"iteration":713,"passed_time":5.041451336,"remaining_time":2.019404877},
{"learn":[0.1606898178],"iteration":714,"passed_time":5.047225231,"remaining_time":2.011831036},
{"learn":[0.1602620758],"iteration":715,"passed_time":5.055613627,"remaining_time":2.00529926},
{"learn":[0.1600749959],"iteration":716,"passed_time":5.061112191,"remaining_time":1.997621688},
{"learn":[0.1597401758],"iteration":717,"passed_time":5.067261971,"remaining_time":1.990205955},
{"learn":[0.1594855858],"iteration":718,"passed_time":5.074162022,"remaining_time":1.983086966},
{"learn":[0.15928435],"iteration":719,"passed_time":5.079412884,"remaining_time":1.975327233},
{"learn":[0.1590109481],"iteration":720,"passed_time":5.088513579,"remaining_time":1.969064201},
{"learn":[0.1587201387],"iteration":721,"passed_time":5.097053717,"remaining_time":1.96257747},
{"learn":[0.1584048532],"iteration":722,"passed_time":5.105792051,"remaining_time":1.956160993},
{"learn":[0.1582651229],"iteration":723,"passed_time":5.11135622,"remaining_time":1.948528062},
{"learn":[0.1580652209],"iteration":724,"passed_time":5.11990304,"remaining_time":1.942032187},
{"learn":[0.1577327009],"iteration":725,"passed_time":5.125726121,"remaining_time":1.934502696},
{"learn":[0.1574690259],"iteration":726,"passed_time":5.136717758,"remaining_time":1.928918773},
{"learn":[0.157343872],"iteration":727,"passed_time":5.160276713,"remaining_time":1.928015475},
{"learn":[0.1569865643],"iteration":728,"passed_time":5.192089306,"remaining_time":1.930118247},
{"learn":[0.1568366087],"iteration":729,"passed_time":5.241724237,"remaining_time":1.938719923},
{"learn":[0.1566691251],"iteration":730,"passed_time":5.258257195,"remaining_time":1.934981102},
{"learn":[0.1564103169],"iteration":731,"passed_time":5.291093657,"remaining_time":1.937176366},
{"learn":[0.1562848376],"iteration":732,"passed_time":5.316053162,"remaining_time":1.936406814},
{"learn":[0.1559648501],"iteration":733,"passed_time":5.347252542,"remaining_time":1.937832665},
{"learn":[0.1558354055],"iteration":734,"passed_time":5.374036392,"remaining_time":1.937577747},
{"learn":[0.1555255863],"iteration":735,"passed_time":5.407368303,"remaining_time":1.9395995},
{"learn":[0.1551954153],"iteration":736,"passed_time":5.45338959,"remaining_time":1.946053544},
{"learn":[0.1550439714],"iteration":737,"passed_time":5.475582081,"remaining_time":1.943905834},
{"learn":[0.1547708104],"iteration":738,"passed_time":5.494419711,"remaining_time":1.940519005},
{"learn":[0.1543863762],"iteration":739,"passed_time":5.511157969,"remaining_time":1.9363528},
{"learn":[0.1540793129],"iteration":740,"passed_time":5.531285823,"remaining_time":1.93333742},
{"learn":[0.1537873766],"iteration":741,"passed_time":5.550934482,"remaining_time":1.930109294},
{"learn":[0.1534164919],"iteration":742,"passed_time":5.564127097,"remaining_time":1.924603855},
{"learn":[0.1532030851],"iteration":743,"passed_time":5.575053102,"remaining_time":1.918297842},
{"learn":[0.1530176691],"iteration":744,"passed_time":5.582037119,"remaining_time":1.910630155},
{"learn":[0.1526540447],"iteration":745,"passed_time":5.593084234,"remaining_time":1.904347715},
{"learn":[0.1521711487],"iteration":746,"passed_time":5.599250182,"remaining_time":1.896399326},
{"learn":[0.1519561312],"iteration":747,"passed_time":5.609694618,"remaining_time":1.889897117},
{"learn":[0.1516833322],"iteration":748,"passed_time":5.624720425,"remaining_time":1.884919662},
{"learn":[0.1513802262],"iteration":749,"passed_time":5.639923092,"remaining_time":1.879974364},
{"learn":[0.1511176084],"iteration":750,"passed_time":5.658212036,"remaining_time":1.876025029},
{"learn":[0.1510047979],"iteration":751,"passed_time":5.674752449,"remaining_time":1.871460914},
{"learn":[0.1508674885],"iteration":752,"passed_time":5.684338441,"remaining_time":1.864583791},
{"learn":[0.1505799768],"iteration":753,"passed_time":5.698672833,"remaining_time":1.859248696},
{"learn":[0.150377898],"iteration":754,"passed_time":5.719621464,"remaining_time":1.856036104},
{"learn":[0.1501927473],"iteration":755,"passed_time":5.738057008,"remaining_time":1.851965489},
{"learn":[0.1500761153],"iteration":756,"passed_time":5.762424551,"remaining_time":1.849761117},
{"learn":[0.1496288217],"iteration":757,"passed_time":5.789215752,"remaining_time":1.848272048},
{"learn":[0.1494011924],"iteration":758,"passed_time":5.814420475,"remaining_time":1.846212562},
{"learn":[0.1489406782],"iteration":759,"passed_time":5.834657852,"remaining_time":1.842523532},
{"learn":[0.148783777],"iteration":760,"passed_time":5.845180144,"remaining_time":1.835739888},
{"learn":[0.1486395286],"iteration":761,"passed_time":5.856484513,"remaining_time":1.829190701},
{"learn":[0.1484520016],"iteration":762,"passed_time":5.870731484,"remaining_time":1.823543069},
{"learn":[0.1482142561],"iteration":763,"passed_time":5.88922142,"remaining_time":1.81918358},
{"learn":[0.1479904147],"iteration":764,"passed_time":5.905920205,"remaining_time":1.814236926},
{"learn":[0.1477316317],"iteration":765,"passed_time":5.917329149,"remaining_time":1.80764363},
{"learn":[0.1475813734],"iteration":766,"passed_time":5.927827632,"remaining_time":1.800761197},
{"learn":[0.1473166016],"iteration":767,"passed_time":5.941853954,"remaining_time":1.794935048},
{"learn":[0.146965202],"iteration":768,"passed_time":5.95778724,"remaining_time":1.789660406},
{"learn":[0.1467042565],"iteration":769,"passed_time":5.9759406,"remaining_time":1.785021218},
{"learn":[0.1464329098],"iteration":770,"passed_time":5.992228356,"remaining_time":1.779792858},
{"learn":[0.1461553446],"iteration":771,"passed_time":6.005657477,"remaining_time":1.773691586},
{"learn":[0.1459513779],"iteration":772,"passed_time":6.015694444,"remaining_time":1.766575212},
{"learn":[0.1456432495],"iteration":773,"passed_time":6.024118173,"remaining_time":1.758980242},
{"learn":[0.1454935096],"iteration":774,"passed_time":6.034525099,"remaining_time":1.7519589},
{"learn":[0.1452437314],"iteration":775,"passed_time":6.050025194,"remaining_time":1.746399025},
{"learn":[0.1449571429],"iteration":776,"passed_time":6.056221129,"remaining_time":1.738143258},
{"learn":[0.1447499992],"iteration":777,"passed_time":6.065800486,"remaining_time":1.730858237},
{"learn":[0.1445027907],"iteration":778,"passed_time":6.071964748,"remaining_time":1.722598472},
{"learn":[0.1442893808],"iteration":779,"passed_time":6.081846327,"remaining_time":1.715392554},
{"learn":[0.144163841],"iteration":780,"passed_time":6.089318958,"remaining_time":1.707504292},
{"learn":[0.1439059211],"iteration":781,"passed_time":6.098470037,"remaining_time":1.700084998},
{"learn":[0.1437732042],"iteration":782,"passed_time":6.104639542,"remaining_time":1.691834969},
{"learn":[0.1436370178],"iteration":783,"passed_time":6.113632061,"remaining_time":1.684368017},
{"learn":[0.1432384333],"iteration":784,"passed_time":6.120500664,"remaining_time":1.676315469},
{"learn":[0.1430960228],"iteration":785,"passed_time":6.131982552,"remaining_time":1.669521967},
{"learn":[0.1428510354],"iteration":786,"passed_time":6.138566212,"remaining_time":1.661390855},
{"learn":[0.1427302429],"iteration":787,"passed_time":6.147600316,"remaining_time":1.653922928},
{"learn":[0.1424745071],"iteration":788,"passed_time":6.153515831,"remaining_time":1.645617035},
{"learn":[0.1422944821],"iteration":789,"passed_time":6.196006773,"remaining_time":1.647039775},
{"learn":[0.1421043178],"iteration":790,"passed_time":6.228726167,"remaining_time":1.645769619},
{"learn":[0.1419886872],"iteration":791,"passed_time":6.248952482,"remaining_time":1.641139036},
{"learn":[0.1418427325],"iteration":792,"passed_time":6.272048153,"remaining_time":1.637218118},
{"learn":[0.1417223054],"iteration":793,"passed_time":6.280747853,"remaining_time":1.629513927},
{"learn":[0.1414626734],"iteration":794,"passed_time":6.288185511,"remaining_time":1.621481798},
{"learn":[0.1412081433],"iteration":795,"passed_time":6.300214996,"remaining_time":1.614627964},
{"learn":[0.1410856941],"iteration":796,"passed_time":6.310620095,"remaining_time":1.607347402},
{"learn":[0.1409533765],"iteration":797,"passed_time":6.318016245,"remaining_time":1.599297345},
{"learn":[0.1407768431],"iteration":798,"passed_time":6.329053324,"remaining_time":1.592164854},
{"learn":[0.1406581352],"iteration":799,"passed_time":6.337393485,"remaining_time":1.584348371},
{"learn":[0.1405860631],"iteration":800,"passed_time":6.346757714,"remaining_time":1.576785},
{"learn":[0.140451714],"iteration":801,"passed_time":6.358895956,"remaining_time":1.569901994},
{"learn":[0.1402792467],"iteration":802,"passed_time":6.365655195,"remaining_time":1.561686268},
{"learn":[0.1401460375],"iteration":803,"passed_time":6.377894114,"remaining_time":1.554810008},
{"learn":[0.1399353574],"iteration":804,"passed_time":6.387422023,"remaining_time":1.54726372},
{"learn":[0.1397383043],"iteration":805,"passed_time":6.399932691,"remaining_time":1.540430449},
{"learn":[0.1395318629],"iteration":806,"passed_time":6.413614095,"remaining_time":1.533863098},
{"learn":[0.1393954957],"iteration":807,"passed_time":6.425879055,"remaining_time":1.526941558},
{"learn":[0.1392175073],"iteration":808,"passed_time":6.432580761,"remaining_time":1.518693357},
{"learn":[0.139074552],"iteration":809,"passed_time":6.442605967,"remaining_time":1.51122856},
{"learn":[0.1388637514],"iteration":810,"passed_time":6.450374596,"remaining_time":1.503231564},
{"learn":[0.1386812332],"iteration":811,"passed_time":6.462144247,"remaining_time":1.496161476},
{"learn":[0.1385113024],"iteration":812,"passed_time":6.474350049,"remaining_time":1.489180146},
{"learn":[0.1383614247],"iteration":813,"passed_time":6.481935342,"remaining_time":1.481130189},
{"learn":[0.138165011],"iteration":814,"passed_time":6.494331586,"remaining_time":1.474173428},
{"learn":[0.1379567916],"iteration":815,"passed_time":6.508035135,"remaining_time":1.467498119},
{"learn":[0.1378076329],"iteration":816,"passed_time":6.519337866,"remaining_time":1.460267845},
{"learn":[0.1375929614],"iteration":817,"passed_time":6.528268593,"remaining_time":1.452499858},
{"learn":[0.1374380205],"iteration":818,"passed_time":6.542264083,"remaining_time":1.445848351},
{"learn":[0.1372638039],"iteration":819,"passed_time":6.555930995,"remaining_time":1.439106804},
{"learn":[0.1371142173],"iteration":820,"passed_time":6.56423071,"remaining_time":1.431178194},
{"learn":[0.1368796477],"iteration":821,"passed_time":6.577943659,"remaining_time":1.42442089},
{"learn":[0.1367116579],"iteration":822,"passed_time":6.592471107,"remaining_time":1.417821854},
{"learn":[0.1364044983],"iteration":823,"passed_time":6.60449112,"remaining_time":1.410668006},
{"learn":[0.1362092672],"iteration":824,"passed_time":6.612945524,"remaining_time":1.40274602},
{"learn":[0.1360281742],"iteration":825,"passed_time":6.625918395,"remaining_time":1.395774577},
{"learn":[0.135893118],"iteration":826,"passed_time":6.63912588,"remaining_time":1.388837699},
{"learn":[0.1357979056],"iteration":827,"passed_time":6.652726206,"remaining_time":1.38196728},
{"learn":[0.1354827187],"iteration":828,"passed_time":6.660644196,"remaining_time":1.373908513},
{"learn":[0.1351967514],"iteration":829,"passed_time":6.672019174,"remaining_time":1.366558144},
{"learn":[0.1350376359],"iteration":830,"passed_time":6.68153634,"remaining_time":1.358820266},
{"learn":[0.1349318289],"iteration":831,"passed_time":6.691788744,"remaining_time":1.351226573},
{"learn":[0.1348124543],"iteration":832,"passed_time":6.704824997,"remaining_time":1.344184603},
{"learn":[0.1344523056],"iteration":833,"passed_time":6.719859826,"remaining_time":1.337526056},
{"learn":[0.1342357985],"iteration":834,"passed_time":6.727385161,"remaining_time":1.329363535},
{"learn":[0.1341747441],"iteration":835,"passed_time":6.738102193,"remaining_time":1.32182866},
{"learn":[0.1340491073],"iteration":836,"passed_time":6.744402026,"remaining_time":1.313425962},
{"learn":[0.1339733521],"iteration":837,"passed_time":6.754211096,"remaining_time":1.30570668},
{"learn":[0.1337773387],"iteration":838,"passed_time":6.76034323,"remaining_time":1.29727683},
{"learn":[0.1335363069],"iteration":839,"passed_time":6.769203351,"remaining_time":1.289372067},
{"learn":[0.1333788305],"iteration":840,"passed_time":6.775095597,"remaining_time":1.280903924},
{"learn":[0.1332543731],"iteration":841,"passed_time":6.785071728,"remaining_time":1.273208234},
{"learn":[0.1331119585],"iteration":842,"passed_time":6.791057931,"remaining_time":1.264764051},
{"learn":[0.1330671335],"iteration":843,"passed_time":6.801132944,"remaining_time":1.257081445},
{"learn":[0.1328640415],"iteration":844,"passed_time":6.806781361,"remaining_time":1.248581196},
{"learn":[0.1326335015],"iteration":845,"passed_time":6.813600942,"remaining_time":1.240300881},
{"learn":[0.1324014024],"iteration":846,"passed_time":6.819365064,"remaining_time":1.231833359},
{"learn":[0.1322894968],"iteration":847,"passed_time":6.824817866,"remaining_time":1.22331641},
{"learn":[0.1319738003],"iteration":848,"passed_time":6.8341783,"remaining_time":1.215501677},
{"learn":[0.1318870351],"iteration":849,"passed_time":6.839414179,"remaining_time":1.206955443},
{"learn":[0.1316408364],"iteration":850,"passed_time":6.847615059,"remaining_time":1.198936127},
{"learn":[0.1314283698],"iteration":851,"passed_time":6.853683542,"remaining_time":1.190545967},
{"learn":[0.1312664378],"iteration":852,"passed_time":6.859253639,"remaining_time":1.182075363},
{"learn":[0.1311727096],"iteration":853,"passed_time":6.866251415,"remaining_time":1.173855628},
{"learn":[0.1309614418],"iteration":854,"passed_time":6.871471402,"remaining_time":1.165337255},
{"learn":[0.1306730199],"iteration":855,"passed_time":6.879420076,"remaining_time":1.15728562},
{"learn":[0.1305022502],"iteration":856,"passed_time":6.884628474,"remaining_time":1.14877698},
{"learn":[0.1302801817],"iteration":857,"passed_time":6.88993743,"remaining_time":1.140292675},
{"learn":[0.1299623251],"iteration":858,"passed_time":6.898438015,"remaining_time":1.132339651},
{"learn":[0.1298494819],"iteration":859,"passed_time":6.904909653,"remaining_time":1.12405506},
{"learn":[0.1296404939],"iteration":860,"passed_time":6.913937147,"remaining_time":1.116187298},
{"learn":[0.1294753209],"iteration":861,"passed_time":6.919761318,"remaining_time":1.107804016},
{"learn":[0.1291814543],"iteration":862,"passed_time":6.928832516,"remaining_time":1.099942126},
{"learn":[0.1290577812],"iteration":863,"passed_time":6.934424594,"remaining_time":1.091529797},
{"learn":[0.1289603001],"iteration":864,"passed_time":6.939942677,"remaining_time":1.083112441},
{"learn":[0.1287819765],"iteration":865,"passed_time":6.948015224,"remaining_time":1.075097044},
{"learn":[0.1286453212],"iteration":866,"passed_time":6.953371088,"remaining_time":1.066664769},
{"learn":[0.1285219222],"iteration":867,"passed_time":6.962345836,"remaining_time":1.05878992},
{"learn":[0.1284126262],"iteration":868,"passed_time":6.967544178,"remaining_time":1.050343254},
{"learn":[0.1283020956],"iteration":869,"passed_time":6.974177528,"remaining_time":1.042118481},
{"learn":[0.1281328878],"iteration":870,"passed_time":6.980465079,"remaining_time":1.033846148},
{"learn":[0.1279604909],"iteration":871,"passed_time":6.985733183,"remaining_time":1.025428724},
{"learn":[0.127857255],"iteration":872,"passed_time":6.994098506,"remaining_time":1.017469084},
{"learn":[0.1276261431],"iteration":873,"passed_time":6.999582691,"remaining_time":1.009093157},
{"learn":[0.1273969061],"iteration":874,"passed_time":7.00784478,"remaining_time":1.001120683},
{"learn":[0.1272689954],"iteration":875,"passed_time":7.013401239,"remaining_time":0.9927645589},
{"learn":[0.1271422996],"iteration":876,"passed_time":7.018582358,"remaining_time":0.9843621779},
{"learn":[0.1269812558],"iteration":877,"passed_time":7.027312137,"remaining_time":0.9764602287},
{"learn":[0.1268325692],"iteration":878,"passed_time":7.032478583,"remaining_time":0.96806588},
{"learn":[0.1267515945],"iteration":879,"passed_time":7.041601911,"remaining_time":0.9602184423},
{"learn":[0.126579298],"iteration":880,"passed_time":7.046957683,"remaining_time":0.9518592103},
{"learn":[0.126432389],"iteration":881,"passed_time":7.052327637,"remaining_time":0.9435086861},
{"learn":[0.126278445],"iteration":882,"passed_time":7.060479556,"remaining_time":0.9355335312},
{"learn":[0.1261095791],"iteration":883,"passed_time":7.06750957,"remaining_time":0.927410758},
{"learn":[0.1260000622],"iteration":884,"passed_time":7.075840655,"remaining_time":0.9194595202},
{"learn":[0.1258700207],"iteration":885,"passed_time":7.081170048,"remaining_time":0.9111212026},
{"learn":[0.1256511925],"iteration":886,"passed_time":7.094529974,"remaining_time":0.903812725},
{"learn":[0.1255202983],"iteration":887,"passed_time":7.10154467,"remaining_time":0.8956903188},
{"learn":[0.1253758607],"iteration":888,"passed_time":7.108416494,"remaining_time":0.8875525656},
{"learn":[0.1252438471],"iteration":889,"passed_time":7.115294529,"remaining_time":0.8794184249},
{"learn":[0.1251173538],"iteration":890,"passed_time":7.122928038,"remaining_time":0.8713795242},
{"learn":[0.1248870317],"iteration":891,"passed_time":7.128119943,"remaining_time":0.8630459124},
{"learn":[0.1247837258],"iteration":892,"passed_time":7.134494495,"remaining_time":0.8548610425},
{"learn":[0.1245198842],"iteration":893,"passed_time":7.140259606,"remaining_time":0.8466079623},
{"learn":[0.1243893471],"iteration":894,"passed_time":7.145364007,"remaining_time":0.8382829281},
{"learn":[0.1241814596],"iteration":895,"passed_time":7.153107213,"remaining_time":0.830271373},
{"learn":[0.1240767141],"iteration":896,"passed_time":7.158102974,"remaining_time":0.8219449345},
{"learn":[0.1239346741],"iteration":897,"passed_time":7.162969799,"remaining_time":0.813611269},
{"learn":[0.1236990096],"iteration":898,"passed_time":7.171154407,"remaining_time":0.805658059},
{"learn":[0.123509357],"iteration":899,"passed_time":7.17646845,"remaining_time":0.7973853833},
{"learn":[0.1233229421],"iteration":900,"passed_time":7.183654107,"remaining_time":0.7893249241},
{"learn":[0.1231003717],"iteration":901,"passed_time":7.189286401,"remaining_time":0.7810976355},
{"learn":[0.1229400982],"iteration":902,"passed_time":7.194908483,"remaining_time":0.7728749976},
{"learn":[0.122714492],"iteration":903,"passed_time":7.202507358,"remaining_time":0.7648680381},
{"learn":[0.1225327268],"iteration":904,"passed_time":7.207799555,"remaining_time":0.7566198428},
{"learn":[0.1224017112],"iteration":905,"passed_time":7.213309322,"remaining_time":0.7484007464},
{"learn":[0.1221403598],"iteration":906,"passed_time":7.220871242,"remaining_time":0.7403980436},
{"learn":[0.1219160378],"iteration":907,"passed_time":7.226352205,"remaining_time":0.7321854657},
{"learn":[0.1218568047],"iteration":908,"passed_time":7.234121713,"remaining_time":0.7242080042},
{"learn":[0.1217098908],"iteration":909,"passed_time":7.239788453,"remaining_time":0.7160230338},
{"learn":[0.1216127248],"iteration":910,"passed_time":7.244726162,"remaining_time":0.7077723693},
{"learn":[0.1214743473],"iteration":911,"passed_time":7.251711485,"remaining_time":0.6997265468},
{"learn":[0.1212122387],"iteration":912,"passed_time":7.257430855,"remaining_time":0.6915624144},
{"learn":[0.1211019857],"iteration":913,"passed_time":7.26674359,"remaining_time":0.6837417383},
{"learn":[0.1209502733],"iteration":914,"passed_time":7.272684429,"remaining_time":0.6756045644},
{"learn":[0.1205776355],"iteration":915,"passed_time":7.280853313,"remaining_time":0.6676765047},
{"learn":[0.1204454161],"iteration":916,"passed_time":7.286945906,"remaining_time":0.6595599893},
{"learn":[0.1202653693],"iteration":917,"passed_time":7.293072206,"remaining_time":0.6514508942},
{"learn":[0.1201617826],"iteration":918,"passed_time":7.302129074,"remaining_time":0.6436044124},
{"learn":[0.1198095198],"iteration":919,"passed_time":7.30755731,"remaining_time":0.6354397661},
{"learn":[0.1196338643],"iteration":920,"passed_time":7.315031728,"remaining_time":0.627456576},
{"learn":[0.1194995132],"iteration":921,"passed_time":7.320137526,"remaining_time":0.6192741074},
{"learn":[0.1193645007],"iteration":922,"passed_time":7.325375512,"remaining_time":0.6111093331},
{"learn":[0.1192224448],"iteration":923,"passed_time":7.332583069,"remaining_time":0.6031128931},
{"learn":[0.1190308838],"iteration":924,"passed_time":7.33824784,"remaining_time":0.5949930681},
{"learn":[0.1188503573],"iteration":925,"passed_time":7.3452594,"remaining_time":0.5869861724},
{"learn":[0.1187779621],"iteration":926,"passed_time":7.350582788,"remaining_time":0.5788484828},
{"learn":[0.1185923159],"iteration":927,"passed_time":7.355674217,"remaining_time":0.5706988617},
{"learn":[0.1184600295],"iteration":928,"passed_time":7.364545113,"remaining_time":0.562844675},
{"learn":[0.118273668],"iteration":929,"passed_time":7.370363363,"remaining_time":0.5547585327},
{"learn":[0.1181683365],"iteration":930,"passed_time":7.376099929,"remaining_time":0.5466712085},
{"learn":[0.1180984243],"iteration":931,"passed_time":7.382491885,"remaining_time":0.5386367469},
{"learn":[0.1179693401],"iteration":932,"passed_time":7.387687982,"remaining_time":0.5305199301},
{"learn":[0.1177642926],"iteration":933,"passed_time":7.395240806,"remaining_time":0.5225759028},
{"learn":[0.1176031271],"iteration":934,"passed_time":7.400973917,"remaining_time":0.5145062082},
{"learn":[0.1174472158],"iteration":935,"passed_time":7.406178671,"remaining_time":0.5064053792},
{"learn":[0.1170995204],"iteration":936,"passed_time":7.413194178,"remaining_time":0.4984324794},
{"learn":[0.1170344915],"iteration":937,"passed_time":7.418651972,"remaining_time":0.4903586591},
{"learn":[0.1169036266],"iteration":938,"passed_time":7.425568927,"remaining_time":0.4823852018},
{"learn":[0.1167424572],"iteration":939,"passed_time":7.430981862,"remaining_time":0.4743179912},
{"learn":[0.1166505866],"iteration":940,"passed_time":7.437316945,"remaining_time":0.4663142399},
{"learn":[0.1165224746],"iteration":941,"passed_time":7.444307794,"remaining_time":0.4583544077},
{"learn":[0.1163941967],"iteration":942,"passed_time":7.449279575,"remaining_time":0.4502745873},
{"learn":[0.116338991],"iteration":943,"passed_time":7.454420769,"remaining_time":0.4422114015},
{"learn":[0.1162235323],"iteration":944,"passed_time":7.461414859,"remaining_time":0.4342622405},
{"learn":[0.1161448268],"iteration":945,"passed_time":7.466862508,"remaining_time":0.4262268239},
{"learn":[0.1160027022],"iteration":946,"passed_time":7.47333801,"remaining_time":0.4182543976},
{"learn":[0.1158854207],"iteration":947,"passed_time":7.478981295,"remaining_time":0.4102394803},
{"learn":[0.1157737956],"iteration":948,"passed_time":7.484003569,"remaining_time":0.4021961876},
{"learn":[0.1156740016],"iteration":949,"passed_time":7.491037394,"remaining_time":0.394265126},
{"learn":[0.1155726335],"iteration":950,"passed_time":7.496348178,"remaining_time":0.3862471722},
{"learn":[0.1152898597],"iteration":951,"passed_time":7.501400556,"remaining_time":0.3782218768},
{"learn":[0.115114444],"iteration":952,"passed_time":7.508257002,"remaining_time":0.3702917934},
{"learn":[0.1150014973],"iteration":953,"passed_time":7.513427705,"remaining_time":0.3622826776},
{"learn":[0.1148323111],"iteration":954,"passed_time":7.518236996,"remaining_time":0.3542624762},
{"learn":[0.1147343372],"iteration":955,"passed_time":7.525551589,"remaining_time":0.3463642991},
{"learn":[0.1145207162],"iteration":956,"passed_time":7.530939222,"remaining_time":0.3383807592},
{"learn":[0.1144442122],"iteration":957,"passed_time":7.537604165,"remaining_time":0.3304586377},
{"learn":[0.1142875626],"iteration":958,"passed_time":7.544319502,"remaining_time":0.3225412926},
{"learn":[0.1140909763],"iteration":959,"passed_time":7.54983741,"remaining_time":0.3145765587},
{"learn":[0.1139626386],"iteration":960,"passed_time":7.557170986,"remaining_time":0.3066906019},
{"learn":[0.1138409609],"iteration":961,"passed_time":7.562790842,"remaining_time":0.2987380998},
{"learn":[0.1137008968],"iteration":962,"passed_time":7.567974673,"remaining_time":0.2907736894},
{"learn":[0.1135714846],"iteration":963,"passed_time":7.574739897,"remaining_time":0.2828741041},
{"learn":[0.1133777159],"iteration":964,"passed_time":7.580444481,"remaining_time":0.2749384009},
{"learn":[0.1132864034],"iteration":965,"passed_time":7.587570239,"remaining_time":0.2670573376},
{"learn":[0.1131055769],"iteration":966,"passed_time":7.592868416,"remaining_time":0.2591154682},
{"learn":[0.1129416867],"iteration":967,"passed_time":7.598003048,"remaining_time":0.2511736545},
{"learn":[0.1127831458],"iteration":968,"passed_time":7.604650581,"remaining_time":0.2432860351},
{"learn":[0.1126312481],"iteration":969,"passed_time":7.609722382,"remaining_time":0.2353522386},
{"learn":[0.1125545107],"iteration":970,"passed_time":7.615134585,"remaining_time":0.2274345036},
{"learn":[0.1122640083],"iteration":971,"passed_time":7.623032459,"remaining_time":0.2195935276},
{"learn":[0.1120791644],"iteration":972,"passed_time":7.628546827,"remaining_time":0.2116862943},
{"learn":[0.1119848743],"iteration":973,"passed_time":7.636109622,"remaining_time":0.2038386552},
{"learn":[0.1118395458],"iteration":974,"passed_time":7.641534363,"remaining_time":0.1959367785},
{"learn":[0.1116890998],"iteration":975,"passed_time":7.646725298,"remaining_time":0.1880342286},
{"learn":[0.1115760243],"iteration":976,"passed_time":7.65368924,"remaining_time":0.1801789688},
{"learn":[0.111455117],"iteration":977,"passed_time":7.65865614,"remaining_time":0.1722806085},
{"learn":[0.1113338162],"iteration":978,"passed_time":7.663814203,"remaining_time":0.1643923373},
{"learn":[0.1112518649],"iteration":979,"passed_time":7.671533866,"remaining_time":0.1565619156},
{"learn":[0.1111102004],"iteration":980,"passed_time":7.677202356,"remaining_time":0.1486919926},
{"learn":[0.1109440451],"iteration":981,"passed_time":7.683827411,"remaining_time":0.140844087},
{"learn":[0.1108879404],"iteration":982,"passed_time":7.689133922,"remaining_time":0.1329758664},
{"learn":[0.1107474566],"iteration":983,"passed_time":7.694332696,"remaining_time":0.1251111008},
{"learn":[0.110671074],"iteration":984,"passed_time":7.701194001,"remaining_time":0.117277066},
{"learn":[0.1106006453],"iteration":985,"passed_time":7.706967782,"remaining_time":0.1094295628},
{"learn":[0.1104681089],"iteration":986,"passed_time":7.712195331,"remaining_time":0.1015790672},
{"learn":[0.1103348334],"iteration":987,"passed_time":7.719382338,"remaining_time":0.09375768022},
{"learn":[0.1101911511],"iteration":988,"passed_time":7.724753751,"remaining_time":0.08591738247},
{"learn":[0.1101087028],"iteration":989,"passed_time":7.729866379,"remaining_time":0.07807945837},
{"learn":[0.1099922885],"iteration":990,"passed_time":7.736712281,"remaining_time":0.0702627755},
{"learn":[0.1098109314],"iteration":991,"passed_time":7.74182038,"remaining_time":0.06243403532},
{"learn":[0.1096586006],"iteration":992,"passed_time":7.74769159,"remaining_time":0.05461615421},
{"learn":[0.1095326013],"iteration":993,"passed_time":7.753448869,"remaining_time":0.04680150222},
{"learn":[0.1093459676],"iteration":994,"passed_time":7.758637837,"remaining_time":0.03898812983},
{"learn":[0.1091622657],"iteration":995,"passed_time":7.766475606,"remaining_time":0.03119066508},
{"learn":[0.1090209656],"iteration":996,"passed_time":7.772467909,"remaining_time":0.02338756643},
{"learn":[0.108840931],"iteration":997,"passed_time":7.77742049,"remaining_time":0.01558601301},
{"learn":[0.1086369373],"iteration":998,"passed_time":7.785179858,"remaining_time":0.007792972831},
{"learn":[0.1085843282],"iteration":999,"passed_time":7.790666097,"remaining_time":0}
]}